{"MPB": {"Djavan": {"url": "djavan", "discography": ["a-carta", "a-idade-do-ceu", "a-ilha", "a-noiva-da-cidade", "a-rosa", "a-rota-do-individuo-ferrugem", "aboio-blues", "acai", "acelerou", "acerto-de-contas", "adorava-me-ver-como-seu", "agua", "agua-de-lua", "alagoas", "alegre-menina", "alem-de-amar", "alias", "alibi", "alivio", "alumbramento", "amar-e-tudo", "amazon-farewell", "amor-algum", "amor-de-indio", "andaluz", "anjo-de-vitro", "ansia-de-viver", "ao-menos-um-porto", "apoteose-ao-samba", "aquele-um", "ares-sutis", "aridez", "asa", "atitude", "aviao", "avo", "azedo-e-amargo", "azul", "bailarina", "baile", "bangalo", "banho-de-rio", "be-fair", "being-cool-aviao", "beiral", "beleza-destruida-com-milton-nascimento", "bicho-solto", "bird-of-paradise", "boa-noite", "bouquet", "brigas-nunca-mais", "brilho-da-noite", "cabeca-vazia", "cair-em-si", "canto-da-lira", "capim", "cara-de-indio", "carnaval-no-rio", "cedo-ou-tarde", "celeuma", "chega-de-magoa", "cigano", "com-mais-ninguem", "como-posso-saber", "coracao-leviano", "cordilheira", "corisco", "correnteza", "curumim", "de-flor-em-flor", "de-tanto-amor", "deixa-o-sol-sair", "delirio-dos-mortais", "desandou", "desejo", "desenho-de-giz", "desfigurado", "dia-azul", "disfarca-e-chora", "doidice", "dois-amores", "dona-do-horizonte", "dor-e-prata", "dores-gris", "dorme-sofia", "dou-nao-dou", "drao", "dupla-traicao", "e-hora", "e-que-deus-ajude", "e-serio", "eh-eh", "embola-bola", "encontrar-te", "enguicado", "entre-outras-mil", "esfinge", "esplendor-part-jorge-drexler", "esquinas", "estatua-de-sal", "estoria-de-cantador", "eu-te-devoro", "extase", "faltando-um-pedaco", "farinha", "fato-consumado", "fera", "figura", "flor-de-lis", "flor-do-medo", "florir", "fly-me-to-the-moon", "humbiumbi", "iluminado", "imposto", "infinito", "infinitude", "iris", "irma-de-neon", "ja-nao-somos-dois", "joaninha", "jogral", "la-noche", "labios", "ladeirinha", "lambada-de-serpente", "lei", "liberdade", "lilas", "limao", "linha-do-equador", "lobisomem", "louca-fina", "luanda", "lugar-comum", "luz", "luz-e-misterio", "maca", "maca-do-rosto", "madressilva", "magia", "mal-de-mim", "malasia", "maledeto", "mande-um-sinal", "maos-dadas", "mar-a-vista", "mar-de-ilusao", "maria-das-mercedes", "matizes", "me-leve", "mea-culpa", "melodia-sentimental", "meninoseu-vi", "meu", "meu-bem-querer", "meu-romance", "mil-vezes", "milagreiro", "minha-irma", "minha-mae", "miragem", "miss-susanna-florir", "morena-de-endoidecer", "muito-mais", "muito-obrigado", "mundo-vasto", "na-boda-do-beco", "nada-a-nos-separar", "nada-mais-sou", "nao-deu", "nao-e-um-bolero", "nas-ruas", "navio", "nem-um-dia", "nereci", "nkosi-sikelel-l-afrika", "nobreza", "num-mundo-de-paz", "numa-esquina-de-hanoi", "nuvem-negra", "nvula-ieza-kia", "o-tal-do-amor", "o-vento", "obi", "oceano", "om", "oracao-ao-tempo", "orquidea", "outono", "palco", "para-comigo-fazer", "para-raio", "passaro", "passou", "pecado", "pedra", "pedro-brasil", "petala", "pode-esquecer", "por-uma-vida-em-paz", "presuncosa", "primazia", "primeira-estrada", "puzzle-of-hearts", "qual-e", "quantas-voltas-da-meu-mundo", "quase-de-manha", "quase-fantasia", "quase-perdida", "que-foi-my-love", "quero-quero", "quinze-anos", "real", "rei-do-mar", "renunciacao", "retrato-da-vida", "reverberou", "ridiculo", "romance", "romeiros", "rua-dos-amores", "sabe-voce", "sabes-mentir", "sabor-impune", "samba-dobrado", "samurai", "se-acontecer", "se-nao-vira-jazz", "se", "se-translation", "seca", "seduzir", "segredo", "sem-saber", "sentimento-verdadeiro", "serrado", "sevilhando", "silaba", "sim-ou-nao", "sina", "so-bashiya-ba-hlala-ekhaya", "so-pra-ser-o-sol", "so-tinha-de-ser-com-voce", "solitude", "sorri", "soweto", "stephens-kingdom", "sururu-de-capote", "taina-flor", "tanta-saudade", "tao-raro", "tarzan-o-filho-do-alfaiate", "tem-boi-na-linha", "temporal", "tenha-calma", "tenho-medo-de-ficar-so", "todas-as-horas", "topazio", "total-abandono", "transe", "treze-de-dezembro", "triste-baia-da-guanabara", "triste-e-o-cara", "um-amor-puro", "um-dia", "um-quase-amor", "uma-brasileira", "vaidade", "valsa-brasileira", "ventos-do-norte", "vesuvio", "vida-nordestina", "vida-real", "vidas-pra-contar", "violeiros", "vive", "viver-e-dever", "voce-bem-sabe", "voce-e", "voce-pode-ser-atriz", "zumbi"]}, "Zé Ramalho": {"url": "ze-ramalho", "discography": ["a-danca-das-borboletas", "a-estrada-de-tijolos-amarelos", "a-nave-interior", "a-noite-branca", "a-noite-preta", "a-peleja-de-ze-limeira-no-final-do-segundo-milenio", "a-peleja-do-diabo-com-o-dono-do-ceu", "a-ultima-nau", "a-unica-coisa-que-eu-quero", "acredite-quem-quiser", "adeus-segunda-feira-cinzenta", "admiravel-gado-novo", "agonico", "agonico-o-canto", "aguas-de-marco", "amalgama", "amanhecer-tantra", "amar-quem-eu-ja-amei", "anuncio-final", "as-aparencias-enganam", "as-aventuras-de-raul-seixas-na-cidade-de-thor", "as-de-espadas", "as-onze-palavras", "asa-branca", "atras-do-balcao", "ave-de-prata", "ave-maria-da-rua", "avohai", "bandeira-desfraldada", "banquete-dos-signos-2", "batendo-na-porta-do-ceu", "batendo-na-porta-do-ceu-versao-2", "be", "beijo-morte-beijo", "beira-mar-capitulo-ii", "beira-mar", "beira-mar-capitulo-final", "beira-mar-a-ressurreicao", "bete-balanco", "bicho-de-sete-cabecas", "brejo-do-cruz", "cacador-de-mim", "cancao-agalopada", "canta-brasil", "cantiga-do-sapo", "caravana", "carcara", "cavalos-do-cao", "chamando-o-silencio", "chao-de-giz", "cidadao", "cidades-e-lendas", "coco-do-trocadilho", "coisas-boas-e-mais", "como-uma-pedra-a-rolar", "companheira-de-alta-luz", "conterraneos", "copula", "coracao-de-rubi", "coracoes-animais", "cristais-do-tempo", "danca-das-luzes", "das-maravilhas", "de-gosto-de-agua-e-de-amigos", "dear-prudence", "decimas-de-um-cantador", "dehra-dun", "dentadura-postica", "desejo-de-mouro", "dia-dos-adultos", "digitado-em-poesia", "disparada", "do-muito-e-do-pouco", "domino", "dona-da-minha-cabeca", "ele-disse", "embolada-violada", "entre-a-serpente-e-a-estrela", "entre-o-ceu-e-o-mar", "errare-humanun-est", "estes-discos-voadores-me-preocupam-demais", "eternas-ondas", "eu-nasci-ha-dez-mil-anos-atras", "eu-vou-pra-lua", "falas-do-povo", "falido-transatlantico", "farol-dos-mundos", "filho-de-icaro", "filhos-do-cancer", "forca-verde", "forrobodo", "fragil", "frevo-mulher", "frevoador", "frisson", "galope-rasante", "garoto-de-aluguel", "garrote-ferido", "gita", "guerra-de-facao", "harmonia-do-amor-com-paula-fernandes", "hino-amizade", "hino-de-duran", "hino-nordestino", "how-could-i-know", "if-not-for-you", "in-my-life", "indo-com-o-tempo", "introito-a-nacao", "isnt-it-a-pity", "jacarepagua-blues", "jardim-das-acacias-ii", "jardins-das-acacias", "just-for-today", "just-for-today-com-rodrigo-santos", "justica-cega", "kamikaze", "knockin-on-heavens-door", "kryptonia", "lamento-cego", "lamento-sertanejo", "lembrancas-do-primeiro", "luciela", "luz-da-excelencia", "made-in-pb", "malandragem-da-um-tempo", "martelo-armagedon", "martelo-rap-ecologico", "mary-mar", "medo-da-chuva", "meninas-de-albara", "meninos-do-sertao", "mesmo-que-seja-eu", "mestica", "metamorfose-ambulante-2", "metropolis-dourada", "meu-bem-querer", "meu-nome-e-trupizupe", "meu-pais", "misterios-da-meia-noite", "modificando-o-olhar", "montarias-sensuais", "mormaco", "mote-das-amplidoes", "mourao-voltado-em-questoes", "mr-pandeiro", "mr-tambourine-man", "mulher-nova-bonita-e-carinhosa", "mulheres", "nao-pense-duas-vezes-ta-tudo-bem-dont-think-twice-its-all-right", "nao-quero-dinheiro-so-quero-amar", "nao-vendo-nem-troco", "napalm", "os-segredos-de-sume", "negro-amor", "nesse-brasil-caboco-de-mae-preta-e-pai-joao", "nunca-deixe-de-sonhar", "o-amanha-e-distante", "o-apocalipse-de-ze-limeira", "o-autor-da-natureza", "o-comeco-da-visao", "o-diagrama-da-alma-dourada", "o-gosto-da-criacao", "o-gosto-fino-das-sensacoes", "o-homem-deu-nome-a-todos-animais", "o-meu-pais", "o-monte-olimpia", "o-norte-do-norte", "o-progresso", "o-que-ainda-vai-nascer", "o-que-e-o-que-e", "o-que-o-mundo-nao-sabe-explicar", "o-que-vale-para-sempre", "o-rei-do-rock", "o-silencio-dos-inocentes", "o-sobrevivente", "o-tolo-na-colina", "o-trem-das-sete", "o-trenzinho-do-caipira", "o-vento-vai-responder", "olhar-alquimista", "olhar-entorpecido", "orquidea-negra", "os-doze-trabalhos-de-hercules", "ouro-de-tolo", "paisagem-da-flor-desesperada", "para-chegar-mais-perto-de-deus", "para-raul", "paraiba", "paralelas", "parceria", "passaros-noturnos", "pau-de-arara", "pedra-templo-animal", "pedras-e-mocas", "pelo-vinho-e-pelo-pao", "pepitas-de-fogo", "planeta-agua", "planos-de-papel", "porta-de-luz", "porta-secreta", "portal-do-destino", "pot-pourri-baiaoimbalancaasa-branca", "pra-nao-dizer-que-nao-falei-de-flores", "preludio", "procurando-a-estrela", "profetas", "quasar-do-sertao", "ratos-de-porto", "repentista-marvel", "rio-paraiba", "rock-feelinngood", "romaria", "s-o-s", "sangue-e-pudins", "sebastiana-um-a-um-chiclete-com-banana", "sem-terra", "sensual", "seres-alados", "serpentaria-everybodys-talking", "sextilhas-filosoficas", "sinais", "sinonimos", "solidao", "sr-ozzy-com-robertinho-de-recife", "ta-tudo-mudando", "taxi-lunar", "temporal", "tempos-modernos", "tocando-em-frente", "tudo-que-fiz-foi-viver", "ultimo-pau-de-arara-2", "um-corpo-que-sai", "um-indio", "um-lugar-para-sonhar", "um-pequeno-xote", "um-pouco-do-que-queira", "vermelhos", "vila-do-sossego", "violar", "visionaria", "visoes-de-ze-limeira-sobre-o-final-do-seculo-xx", "voa-voa", "voce-ainda-pode-sonhar-lucy-in-the-sky-with-diamonds", "voce-se-lembra", "wingman", "xote-dos-poetas", "zyliana"]}, "Chico Buarque": {"url": "chico-buarque", "discography": ["a-aurora-de-nova-iorque", "a-banda", "a-bela-e-a-fera", "a-cidade-dos-artistas", "a-cidade-ideal", "a-foto-da-capa", "a-galinha", "a-historia-de-lily-braun", "a-mais-bonita", "a-moca-do-sonho", "a-mulher-de-cada-porto", "a-mulher-do-anibal-dueto-com-zeca-pagodinho", "a-noiva-da-cidade", "a-ostra-e-o-vento", "a-permuta-dos-santos", "a-pousada-do-bom-barao", "a-rita", "a-rosa", "a-televisao", "a-valsa-dos-clowns", "a-violeira", "a-volta-do-malandro", "a-voz-do-dono-e-o-dono-da-voz", "abandono", "acalanto", "acalanto-acalanto", "acalanto-en-espanol", "acalanto-para-helena", "acorda-amor", "agora-falando-serio", "ai-se-eles-me-pegam-agora", "almanaque", "alo-liberdade", "alumbramento", "amando-sobre-os-jornais", "amanha-ninguem-sabe", "amor-barato", "ana-de-amsterdam", "anema-e-core", "angelica", "ano-novo", "anos-dourados", "apesar-de-usted-apesar-de-voce", "apesar-de-voce", "aquela-mulher", "as-atrizes", "as-caravanas", "as-cartas", "as-minhas-meninas", "as-vitrines", "assentamento", "ate-o-fim-letras", "ate-pensei", "ate-segunda-feira", "atras-da-porta", "baioque", "bancarrota-blues", "bandolim", "barafunda", "barbara", "basta-um-dia", "bastidores", "baticum", "beatriz-letras", "bem-querer", "benvinda", "bicharia", "biscate", "blues-pra-bia", "boi-voador-nao-pode", "bolero-blues", "bom-conselho", "bom-tempo", "brejo-da-cruz", "bye-bye-brasil", "ce-piu-samba", "ca-sert-a-quoi", "cacada", "cade-voce", "cala-a-boca-barbara", "calice-part-milton-nascimento", "cambaio", "camisola-do-dia", "cancao-de-pedroca", "cancao-dos-olhos", "cantando-no-toro", "cantiga-de-acordar", "cantores-do-radio", "capital-do-samba", "cara-a-cara", "carcara", "carioca", "carolina", "carta-do-tom-parodia", "caruso", "casa-de-joao-de-rosa", "casualmente", "cecilia", "cem-mil-reis", "chao-de-esmeraldas", "chega-de-magoa", "choro-bandido", "ciao-ciao-addio", "ciranda-da-bailarina", "cobra-de-vidro", "com-acucar-com-afeto", "como-se-fosse-a-primavera", "como-um-samba-de-adeus", "construcao", "construccion", "construcion-dios-le-pague", "conversa-de-botequim", "copo-vazio", "cordao", "corrente", "cotidiano", "cotidiano-en-espanol", "cuidado-com-a-outra", "de-todas-as-maneiras", "de-volta-ao-samba", "deixa-a-menina", "deixe-a-menina", "desafio-do-malandro", "desaforos", "desalento", "desembolada", "desencanto", "desencontro", "deus-lhe-pague", "dinheiro-em-penca", "dis-mois-comment", "divina-dama", "doze-anos", "dr-getulio", "duas-vezes-escrava", "dueto", "dueto-part-clara-buarque", "dura-na-queda", "e-se", "e-tao-simples", "ed-ora-dico-sul-serio-agora-falando-serio", "ela-desatinou", "ela-e-dancarina", "ela-e-sua-janela", "ela-faz-cinema", "embarcacao", "embebedado", "embolada", "ensaio-geral", "esconde-esconde", "essa-moca-ta-diferente", "essa-passou", "essa-pequena", "estacao-derradeira", "estamos-ai", "eu-sou-a-arvore", "eu-te-amo", "exaltacao-a-mangueira", "facamos", "fado-tropical", "fantasia", "far-niente-bom-tempo", "feijoada-completa", "festa-imodesta", "fica", "filosofia", "flor-da-idade", "foi-assim", "folhetim", "fora-de-hora", "forrobodo", "fortaleza", "frevo-diabo", "funeral-de-um-lavrador", "funerale-di-un-contadino", "futuros-amantes", "geni-e-o-zepelim", "geni-y-el-zepelin-geni-e-o-zepelim", "geni-y-el-zepelin-geni-e-o-zepelin", "gente-humilde", "gota-dagua", "grande-hotel", "hino-da-repressao", "hino-de-duran", "historia-de-uma-gata", "hollywood", "homenagem-ao-malandro", "homens-de-pedra", "il-nicanor-il-marinaio", "il-nome-di-maria-nao-fala-de-maria", "ilmo-sr-ciro-monteiro", "imagina", "imagina-so", "in-memoria-di-un-congiurate", "in-te-mulher-vou-dizer-quanto-te-amo", "injuriado", "introducao-para-a-turma-do-funil", "iolanda", "iracema-voou", "ja-passou", "janelas-abertas-numero-2", "januaria", "joana-francesa", "joao-e-maria", "jogo-de-bola", "jorge-maravilha", "juca", "juca-italiano", "la-banda", "la-rita-a-rita", "la-tv", "labareda-homenagem-a-joao-nogueira", "labia", "lagrima", "las-muchachas-de-copacabana", "lei-no-lei-sta-ballando", "leo", "levantados-do-chao", "leve", "ligia", "linguagem-do-morro", "linha-de-montagem", "logo-eu", "lola", "lua-cheia", "ludo-real", "luisa", "madalena-foi-pro-mar", "maddalena-e-andata-via", "mais-uma-estrela", "malandro-quando-morre", "mambembe", "mambembe-en-espanol", "mambembe-mambembe", "mambordel", "maninha", "mano-a-mano", "mar-e-lua", "mar-y-luna-mar-e-lua", "maravilha", "marcha-para-um-dia-de-sol", "massarandupio", "me-deixe-mudo", "meia-noite", "meio-dia-meia-lua", "meninos-eu-vi", "meu-caro-amigo", "meu-caro-barao", "meu-namorado", "meu-refrao", "mil-perdoes", "milagre-brasileiro", "minha-cancao", "minha-embaixada-chegou", "minha-historia", "morena-de-angola", "morena-dos-olhos-dagua", "morena-dos-olhos-dagua-2", "morro-dois-irmaos", "morte-e-vida-severina", "moto-continuo", "mulher-na-janela", "mulher-vou-dizer-quanto-te-amo", "mulheres-de-atenas", "mundo-de-zinco", "murro-em-ponta-de-faca", "na-carreira", "na-ilha-de-lia-no-barco-de-rosa", "nao-existe-pecado-ao-sul-do-equador", "nao-fala-de-maria", "nao-sonho-mais", "nego-maluco", "nicanor", "nina", "noite-de-verao", "noite-dos-mascarados", "non-vuoi-ascoltare", "nosso-bolero", "noticia-de-jornal", "novicia", "novo-amor", "nuvem-negra-com-djavan-e-gal-costa", "o-caderno", "o-casamento-dos-pequenos-burgueses", "o-cio-da-terra", "o-circo-mistico", "o-corsario-do-rei", "o-filho-que-eu-quero-ter", "o-futebol", "o-jumento", "o-malandro", "o-malandro-no-2", "o-meu-amor", "o-meu-guri", "o-que-sera-a-flor-da-pele", "o-que-sera-a-flor-da-terra", "o-que-sera-abertura", "o-rei-de-ramos", "o-ultimo-blues", "o-velho", "o-velho-francisco", "ode-aos-ratos", "oh-che-sara", "ole-ola", "ole-ola-italiano", "olha", "olha-maria", "olhos-nos-olhos", "onde-e-que-voce-estava", "opera", "opereta-do-casamento", "opereta-do-moribundo", "os-grilos-sao-astros", "outra-noite", "outros-sonhos", "pagodespell", "palavra-de-mulher", "paratodos", "paroara", "partido-alto", "passara", "passaredo", "pedaco-de-mim-part-zizi-possi", "pedro-pedreiro", "pedro-pedreiro-italiano", "pelas-tabelas", "pequena-serenata-diurna", "piano-na-mangueira", "piruetas", "pivete", "pois-e", "porque-era-ela-porque-era-eu", "primeiro-de-maio", "prologo", "quadrilha", "qualquer-amor", "qualquer-cancao", "quando-o-carnaval-chegar", "que-tal-um-samba", "quem-te-viu-quem-te-ve", "querido-diario", "queste-e-quelle-umas-e-outras", "realejo", "rebichada", "renata-maria", "retrato-em-branco-e-preto", "rio-42", "roda-gigante", "roda-viva", "romance", "rosa-dos-ventos", "rotativa", "rotativa-roda-viva", "rubato", "sabado-a-noite", "sabia", "sala-de-recepcao", "salmo", "samba-da-boa-vontade", "samba-de-orly", "samba-do-grande-amor", "samba-e-amor", "samba-e-amore-samba-e-amor", "samba-para-vinicius", "se-eu-fosse-o-teu-patrao", "se-eu-soubesse", "sem-acucar", "sem-compromisso", "sem-fantasia", "sem-voce", "sem-voce-n-2", "sempre", "sentimental", "sera-que-cristina-volta", "seu-chopin-desculpe", "severino-o-rio", "show-bizz", "silvia", "sinal-fechado", "sinha", "sinhazinha-despedida", "sinhazinha-despertar", "sob-medida", "sobre-todas-as-coisas", "sogno-di-un-carnevale", "sol-e-chuva", "soneto", "sonho-de-um-carnaval", "sonho-impossivel", "sonhos-sonhos-sao", "sou-eu", "suburbano-coracao", "suburbio", "supoe", "tablados", "tamandare", "tango-de-nancy", "tango-do-covil", "tanta-saudade", "tantas-palavras", "tanto-amar", "tanto-mar", "tanto-mar-1-versao", "tatuagem", "tem-mais-samba", "tema-de-os-inconfidentes", "tempo-e-artista", "teresinha", "tereza-tristeza", "tipo-um-baiao", "tira-as-maos-de-mim", "todo-o-sentimento", "todos-juntos", "tororo", "trapacas", "trocando-em-miudos", "tu-sei-una-di-noi-quem-te-viu-quem-te-ve", "tua-cantiga", "um-chorinho", "um-dia-de-cao", "um-tempo-que-passou", "uma-cancao-desnaturada", "uma-cancao-inedita", "uma-menina", "uma-palavra", "umas-e-outras", "una-mia-canzone", "vai-levando", "vai-passar", "vai-trabalhar-vagabundo", "valsa-brasileira", "valsa-dos-clowns", "valsa-rancho", "valsinha", "vence-na-vida-quem-diz-sim", "veneta", "verdadeira-embolada", "vida-nao-cifrada", "viver-do-amor", "voce-nao-entende-nada", "voce-nao-ouviu", "voce-nao-sabe-amar", "voce-vai-me-seguir", "voce-voce", "voltei-a-cantar-mambembe-dura-na-queda", "voo-cego", "xote-de-navegacao", "yes-ze-manes", "yolanda-espanhol"]}, "Gal Costa": {"url": "gal-costa", "discography": ["70-neles", "a-guerra-dos-mascates", "a-mulher", "a-coisa-mais-linda-que-existe", "a-felicidade", "a-historia-de-lily-braun", "a-linha-e-o-linho", "a-preta-do-acaraje", "a-ra", "a-rita", "a-tenda", "a-verdadeira-baiana", "a-voz-do-tambor", "abandono", "abre-alas-do-verao", "acai", "acaua", "acende-o-crepusculo", "acontece", "acorda-pra-cuspir", "aguarte-agora", "alcohol", "aguem-como-tu", "alguem-me-disse", "alkahool", "amor-ate-o-fim-com-elis-regina", "amor-de-juventud", "amor-se-acalme", "anos-dourados", "antonico", "anuviar", "aquarela-do-brasil", "aquele-frevo-axe", "arara", "as-rosas-nao-falam", "as-time-goes-by", "as-vitrines", "assum-branco", "assum-preto", "ate-amanha", "ate-quem-sabe", "atimo-de-som", "atras-da-luminosidade", "atras-da-porta", "autotune-autoerotico", "avarandado", "ave-maria-do-morro", "ave-nossa", "azul", "baby", "bahia-de-todas-as-contas", "bahia-minha-preta", "balance", "barato-total", "begin-the-beguine", "bem-bom", "bem-me-quer", "bloco-do-prazer", "bonita", "borzeguim", "bota-a-mao-nas-cadeiras", "brasil", "brigas", "brigas-nunca-mais", "brilho-de-beleza", "bumbo-da-manguira", "cabeca-feita-tillingo-tem-pouca-diferenca", "cabelo", "cabelos-e-unhas", "cada-macaco-no-seu-galho-cho-chua", "cade", "cajuina", "calling-you", "caminhos-cruzados", "caminhos-do-mar", "camisa-amarela", "cancao-que-morre-no-ar", "candeias", "canta-brasil", "cara-do-mundo", "caras-e-bocas", "cartao-postal", "casca", "charles-anjo-45", "chega-de-saudade", "chiclete-com-banana", "chora-tua-tristeza", "chovendo-na-roseira", "chululu", "chuva-de-prata", "chuva-suor-e-cerveja", "cinema-olympia", "clara", "clario", "coisa-mais-linda", "com-medo-com-pedro", "como-2-e-2", "como-um-samba-de-adeus", "contigo-aprendi", "copacabana", "coracao-vagabundo", "corcovado", "creio", "cuidando-de-longe-part-marilia-mendonca", "cultura-e-civilizacao", "da-maior-importancia", "dama-sofisticada-sophisticated-lady", "de-amor-eu-morrerei", "de-flor-em-flor", "de-fogo-luz-e-paixao", "de-onde-vem-o-baiao", "de-um-role", "de-volta-ao-comeco", "de-volta-ao-futuro", "deixa-sangrar", "dentro-da-lei", "derradeira-primavera", "desafinado", "desalento", "desde-que-o-samba-e-samba", "detalhes", "deus-e-o-amor", "dez-anjos", "dez-anos-diez-anos", "dindi", "divino-maravilhoso", "dois-de-fevereiro", "dom-de-iludir", "domingo", "dono-dos-teus-olhos", "e-doxum", "e-dai", "e-luxo-so", "ecstasy", "embebedado", "epitafio", "erratica", "escandalosa", "esoterico", "espelho-dagua", "esquadros", "esquecendo-voce", "estrada-do-sol", "estratosferica", "estrela-estrela", "eternamente", "eu-acredito", "eu-sou-terrivel", "eu-te-amo", "faceira", "falando-de-amor", "falsa-baiana", "faltando-um-pedaco", "festa-de-rua", "festa-do-interior", "fim-de-caso", "fita-amarela", "flor-de-maracuja", "flor-do-cerrado", "folha-morta", "folhas-secas", "folhetim", "fon-fon", "forca-estranha", "fotografia", "frevo", "fruta-gogoia", "futuros-amantes", "garota-de-ipanema", "goleiro-eu-vou-lhe-avisar", "grande-final", "gratitude", "groupie", "habib", "hoje", "holofotes", "hotel-das-estrelas", "i-didnt-know-what-time-it-was", "ilusao-a-toa", "imunizacao-racional-que-beleza", "india", "inquietacao", "ja-era-tempo", "jabitaca", "janelas-abertas", "jogada-pelo-mundo", "joia", "jovens-tardes-de-domingo", "jurei", "juventude-transviada", "kalu", "lagrimas-negras", "lanterna-dos-afogados", "lavagem-do-bonfim", "ligia", "linda-flor", "lindeza", "lingua", "lingua-do-p", "livre-do-amor", "logus-pe", "london-london", "lost-in-the-paradise", "louca-me-chamam", "love-try-and-die", "lua-de-mel", "lua-lua-lua-lua", "luto", "luz-do-sol", "luz-do-sol-disco-fatal", "madredeus", "mae", "mae-da-manha", "mae-de-todas-vozes", "mal-secreto", "mamae-coragem", "mansidao", "mar-e-sol", "maria-bethania", "maria-joana", "massa-real", "me-faz-bem", "me-recuso", "merceditas", "meu-bem-meu-mal", "meu-doce-amor", "meu-nome-e-gal", "meu-primeiro-amor", "miami-maculele", "mil-perdoes", "milagres-do-povo", "milho-verde", "minha-estrela-e-do-oriente", "minha-mae-part-maria-bethania", "minha-senhora", "minha-voz-minha-vida", "mini-misterio", "modinha-para-gabriela", "morena-dos-olhos-dagua", "morro-de-saudade", "muita-sorte", "muito-por-demais", "mulher-sexo-fragil", "musa-cabocla", "musa-de-qualquer-estacao", "na-baixa-do-sapateiro", "nada-a-ver", "nada-mais", "namorinho-de-portao", "nao-identificado", "negro-amor", "neguinho", "nem-eu", "nenhuma-dor", "nervos-de-aco", "no-tabuleiro-da-baiana", "noites-cariocas", "nossos-momentos", "novo-amor", "nua-ideia-leial-xii", "nuvem-negra", "ressuscita-me", "o-amor-em-paz", "o-bater-do-tambor", "o-bem-do-mar", "o-ceu-e-o-som", "o-ciume", "o-cu-do-mundo", "o-gosto-do-amor", "o-menino", "o-oravalho-vem-caindo", "o-que-e-que-ha", "o-quereres", "o-revolver-do-meu-sonho", "o-ultimo-blues", "o-vento", "objeto-sim-objeto-nao", "odara", "olha", "olhos-do-coracao", "olhos-verdes", "onde-deus-possa-me-ouvir", "onde-esta-o-dinheiro", "onde-eu-nasci-passa-um-rio", "oracao-de-ma-menininha", "ovelha-negra", "pais-tropical", "palavras-do-corpo", "palavras-no-corpo", "palpite-infeliz", "passarinho", "paula-e-bebeto", "pedaco-de-mim", "pegando-fogo", "peguei-um-ita-no-norte", "pela-luz-dos-olhos-teus", "pelos-olhos", "perola-negra", "pescaria-canoeiro", "piano-na-mangueira", "pois-e", "ponta-de-areia", "pontos-de-luz", "por-baixo", "por-causa-de-voce", "pra-machucar-meu-coracao", "pra-que-cantar", "pra-voce", "presente-cotidiano", "pulsars-e-quasars", "puro-sangue-libelo-do-perdao", "qual-e-baiana", "quando-eu-fecho-os-olhos", "quando-voce-olha-pra-ela", "quase-um-segundo", "que-maravilha", "que-pena", "quem-me-dera", "quem-perguntou-por-mim", "quem-te-viu-quem-te-ve", "qui-nem-jilo", "rainha-do-mar", "realmente-lindo", "recanto-escuro", "relance", "remelexo", "resposta", "revolta-olodum", "roda-baiana", "romance", "ruas-de-outono", "rumba-louca", "sabado-em-copacabana-copacabana", "salvador-nao-inerte-ladeira-do-pelo", "samba-do-aviao", "samba-do-grande-amor", "samba-rasgado", "santana", "sao-salvador", "saudosismo", "se-todos-fossem-iguais-a-voce", "se-voce-pensa", "sebastiana", "segunda", "sem-grilos", "sem-medo-nem-esperanca", "serene", "sertao", "sexo-e-dinheiro", "sexo-e-luz", "sim-ou-nao", "simples-carinho", "so-louco", "socorro", "solar", "solidao-o-dono-do-mundo", "solitude", "sonho-real", "sorte-part-caetano-veloso", "sou-mais-eu", "sua-estupidez", "sublime", "sutis-diferencas", "tapete-magico", "te-adorar", "teco-teco", "tema-de-amor-de-gabriela", "the-archaic-lonely-star-blues", "the-empty-boat", "the-fool-on-the-hill", "tigresa", "tocarte-com-nando-reis-e-gilberto-gil", "todo-amor-que-houver-nessa-vida", "todos-os-instrumentos", "topazio", "trem-das-onze", "tropicalia", "tu", "tuareg", "tudo-doi", "ultimo-blues", "um-dia", "eu-preciso-te-falar", "um-favor", "um-gosto-de-sol", "um-passo-a-frente", "vaca-profana-2", "vapor-barato", "vapor-baratoflor-da-pele", "vatapa", "veneta", "verbos-do-amor", "viagem-passageira", "vida-de-artista", "vida-que-segue", "viver-e-reviver-here-there-and-everywere", "voce", "voce-e-voce", "voce-me-deu", "voce-nao-entende-nada", "voce-nao-gosta-de-mim", "volta", "vou-buscar-voce-pra-mim", "vou-recomecar", "voyeur", "wave", "zabele", "zanzando"]}, "Jorge Ben Jor": {"url": "jorge-ben-jor", "discography": ["a-banda-do-ze-pretinho", "a-bencao-mamae-a-bencao-papai", "a-cegonha-me-deixou-em-madureira", "a-fonte-de-paulus-v", "a-historia-de-jorge", "a-jovem-samba", "a-lingua-dos-anjos", "a-loba-comeu-o-canario", "a-lua-e-minha", "a-minha-menina", "a-princesa-e-o-plebeu-o-plebeu", "a-rainha-foi-embora", "a-tamba", "a-terra-do-filho-do-homem", "acende-o-fogo", "adelita", "africa-brasil-zumbi", "agamamou", "agora-ninguem-chora-mais", "alcohol", "aleluia-aleluia-e-ainda-tem-mais", "alfredin", "alo-alo-como-vai", "amante-amado", "amor-de-carnaval", "ana-tropicana", "anjo-azul", "apareceu-aparecida", "ariana-mas-que-nada", "as-rosas-eram-todas-amarelas", "assim-falou-santo-tomaz-de-aquino", "ave-anjos-angeli", "bahia-berco-do-brasil", "balanca-pema", "barbarella", "bebete-vaobora", "berenice", "bicho-do-mato", "bizantina-bizancia", "boiadeiro", "bom-dia-boa-tarde-boa-noite-amor", "bom-mesmo-e-amar", "brother", "bumbo-da-mangueira", "c-589", "cabelo", "cade-o-penalty", "cade-tereza", "cae-cae-caetano", "cafe", "camisa-10-da-gavea", "camisa-12", "cancao-de-uma-fa", "cantilenas-de-sao-victor", "capoeira", "caramba-galileu-da-galileia", "carnaval-triste", "carolina-carol-bela", "cassius-marcelo-clay", "cavaleiro-do-cavalo-imaculado", "charles-jr", "charles-anjo-45", "chove-chuva", "cigana", "cinco-minutos", "comanche", "conquero", "cosa-nostra", "costa-do-marfim", "cowboy-jorge", "criola", "cuidado-com-o-bulldog", "curumim-chama-cunhata-que-eu-vou-contar-todo-dia-era-dia-de-indio", "dadiva-da-da", "danca-que-isso-e-sambafoxe", "dandara-hey", "deixa-o-menino-brincar", "denize-rei", "descalco-no-parque", "descobri-que-sou-um-anjo", "desligado", "do-leme-ao-pontal", "domenica-domingava-num-domingo-linda-toda-de-branco", "domingas", "domingo-23", "dona-culpa", "dorothy", "duas-mulheres", "dumingaz", "dzarm", "e-so-sambar", "ela-mora-em-matogrosso-fronteira-com-o-paraguai", "ela-mora-na-pavuna", "elizabeth-blue", "emilio", "emo", "energia-bom-bom", "engenho-de-dentro", "era-uma-vez-13-pontos", "era-uma-vez-um-aposentado-marinheiro", "errare-humanum-est", "espero-por-voce", "eu-bem-que-lhe-avisei", "eu-quero-ver-a-rainha", "eu-sou-cruel", "eu-sou-da-pesada", "eu-vou-torcer", "falsa-magra", "filho-maravilha", "filhos-de-gandhi", "fio-maravilha", "flamengo", "forca-bruta", "frases", "funk-astrid", "gabriel-guerreiro-galactico", "gabriel-rafael-miguel", "gabriela", "gama-gush", "georgia-e-jorge", "gertrudes-bonhausen", "gimbo", "goleiro-eu-vou-lhe-avisar", "gostosa", "guerreiro-do-rei", "heavy-samba-para-um-poeta-amigo-meu", "hermes-trismegisto-e-sua-celeste-tabua-de-esmeralda", "hermes-trismegisto-escreveu", "hino-do-flamengo", "hino-oficial-do-clube-de-regatas-flamengo", "historia-do-homem", "hoje-e-dia-de-festa", "homem-de-negocios", "homem-do-espaco", "homo-sapiens", "hooked-on-samba", "irene-cara-mia", "ive-brussel", "janaina-argentina", "jazz-potatoes", "jeitao-de-preto-velho", "jesualda", "jorge-da-capadocia", "jorge-well", "jovem-samba", "katarina-katarina", "la-vem-salgueiro", "ladrao-batuta", "lady-benedicta", "lalari-olala", "coisa-de-jorge", "little-black-joes-band", "lorraine", "luiz-wagner-guitarreiro", "luz-polarizada", "ma-ma-ma-ma-mae-a-lingua-dos-anjos", "magnolia", "mama-africa", "mano-caetano", "maria-conga", "maria-domingas", "maria-helena-e-chiquinho", "maria-luiza", "mais-que-nada", "me-chamando-de-paixao", "menina-bonita-nao-chora", "menina-crioula", "menina-do-vestido-coral", "menina-gata-augusta", "menina-mulher-da-pele-preta", "menino-jesus-de-praga", "meu-glorioso-sao-cristovao", "meus-filhos-meu-tesouro", "mexe-mexe", "minha-estrela-e-do-oriente", "minha-menina", "minha-princesa", "minha-teimosia-e-uma-arma-pra-te-conquistar", "miss-mexe-gal", "miss-x", "moca", "moca-bonita", "mona-lisa-mona-lisa-ciumes-de-leonardo", "morre-o-burro-fica-o-homem", "mulher-brasileira", "mulheres-no-volante", "my-lady", "my-little-brother", "na-bahia-tem", "nao-desanima-joao", "nascimento-de-um-principe-africano", "natal-brasileiro", "negro-e-lindo", "nena-nana", "no-reino-encantado-do-amor", "norma-jean", "o-amante-vigilante-africano", "o-astro", "o-circo-chegou", "o-comilao", "o-dia-que-o-sol-declarou-o-seu-amor-pela-terra", "o-filosofo", "o-homem-da-gravata-florida", "o-homem-que-matou-o-homem-que-matou-o-homem-mau", "o-namorado-da-viuva", "o-nome-do-rei-e-pele", "o-plebeu", "o-rei-chegou-viva-o-rei", "o-rei-e-rosa-cruz", "o-sabor-poetico-da-literatura-de-cordel", "o-telefone-tocou-novamente", "oba-la-la", "oba-la-vem-ela", "obsessao-meu-amor", "occulatus-abis", "oe-oe-faz-o-carro-de-boi-na-estrada", "ogum", "olha-a-beleza-dela", "olha-a-pipa", "olha-o-menino", "onde-anda-o-meu-amor", "os-alquimistas-estao-chegando", "os-cavaleiros-do-rei-arthur", "pais-tropical", "pais-tropicalspyro-gyro", "palco", "palomaris", "pancada-de-amor-nao-doi", "para-ouvir-no-radio-luciana", "para-que-digladiar", "patapatapata", "paz-e-arroz", "pega-ela-de-montao", "pelos-verdes-mares", "pisada-de-elefante", "pois-e", "ponta-de-lanca-africano-umbabarauma", "por-causa-de-voce-menina", "por-causa-de-voce-meninachove-chuvamas-que-nada", "por-que-e-proibido-pisar-na-grama", "princesa", "princesa-e-o-plebeu", "procura-se-uma-noiva", "pula-bau", "pulo-pulo", "quanto-mais-te-vejo", "quase-colorida-verushka", "que-maravilha", "que-nega-e-essa", "que-pena", "quem-cochicha-o-rabo-espicha", "quem-mandou-pe-na-estrada", "quem-roubou-a-sopeira-de-porcelana-chinesa-que-a-vovo-ganhou-da-baronesa", "queremos-guerra", "quero-esquecer-voce", "quero-toda-noite", "rabo-preso", "rio-babilonia", "rita-jeep", "roberto-corta-essa", "rosa-mas-que-nada", "rosa-menina-rosa", "saida-do-porto", "saint-leibowitz", "salve-simpatia", "salve-simpatia-a-banda-do-ze-pretinho", "salve-se-quem-puder", "samba-legal", "samba-menina", "santa-clara-clareou", "sao-e-salvos", "sarro", "sasaci-perere", "se-segura-malandro", "selassie", "senhora-dona-da-casa", "si-manda", "solitario-surfista", "sou-da-pesada", "spirogyra-story", "spyro-gyro", "surfista-solitario", "ta-na-hora", "taj-mahal", "taj-mahal-fio-maravilha-pais-tropical", "take-it-easy-my-brother-charles", "te-te-te-te-te-te-tereza", "telefone-de-brotinho", "terezinha", "tim-dom-dom", "to-com-deus-to-com-amor", "toda-colorida", "troca-troca", "tupinambas", "turba-philosoforum", "uala-uala-la", "ubirani-ubiraci", "um-aviao-me-informou", "umbabarauma-part-mano-brown", "usted-es-mi-marron-glase", "vamos-embora-uau", "velhos-flores-criancinhas-e-cachorros", "vem-morena-vem", "vendedor-de-bananas", "vinheta", "viva-sao-pedro", "vou-andando", "vou-de-samba-com-voce", "wbrasil-chama-o-sindico", "waimea-55-000", "waldomiro-pena", "xica-da-silva", "zagueiro", "zazueira", "ze-blueman", "ze-canjica", "zenon-zenon", "zope-zope", "zula", "zumbi"]}, "Gilberto Gil": {"url": "gilberto-gil", "discography": ["17-leguas-e-meia", "2001", "a-agua-benta", "a-bruxa-de-mentira", "a-cegonha-me-deixou-em-madureira", "a-ciencia-em-si", "a-coisa-mais-linda-que-existe", "a-faca-e-o-queijo", "a-forca-secreta-daquela-alegria", "a-gaivota", "a-historia-da-nossa-ilusao", "a-linha-e-o-linho", "a-luta-contra-a-lata-ou-a-falencia-do-cafe", "a-mao-da-limpeza", "a-moreninha", "a-morte", "a-noticia", "a-novidade", "a-paz", "a-raca-humana", "a-rita", "a-rua", "a-sociedade-afluente", "a-ultima-valsa", "a-volta-da-asa-branca", "a-voz-do-vivo", "aboio", "abra-o-olho", "abri-a-porta", "abrir-a-porta-pra-voce", "acertei-no-milhar", "afogamento-part-roberta-sa", "afoxe-e", "africaner-brother-bound", "agua-de-meninos", "alagados", "alapala-the-myth-of-shango", "altos-e-baixos", "amarra-o-teu-arado-a-uma-estrela", "amiga-dos-ventos", "amo-tanto-viver", "amor-ate-o-fim", "amor-de-carnaval", "andar-com-fe", "aos-pes-da-cruz", "aprendi-com-o-rei", "aquele-abraco", "aqui-e-agora", "aroma", "as-ayabas", "as-camelias-do-quilombo-do-leblon", "as-coisas", "as-folhas-verdes-de-verao", "as-pegadas-do-amor", "asa-branca", "assim-sim", "assum-preto", "atimo-de-po", "atras-do-trio", "baba-alapala", "babylon", "back-in-bahia", "bacurizim", "bahia-de-todas-as-contas", "baiao-atemporal", "baiao-da-penha", "balada-do-lado-sem-luz", "balafon", "bale-da-bola-copa-98", "bale-de-berlim", "banda-larga-cordel", "banda-um", "barato-total", "barca-grande", "bat-staka", "batmacumba", "beira-mar", "belo-dia", "bem-devagar", "brand-new-dream", "brazil-very-happy-band", "buda-nago", "buffalo-soldier", "cada-macaco-no-seu-galho", "cada-tempo-em-seu-lugar", "cajuina-refazenda", "cambalache", "cant-find-my-way-home", "cancao-da-moca", "cano", "cantiga-do-sapo", "canto-da-ema", "cara-a-cara", "carta-a-mae", "casinha-feliz", "cerebro-eletronico", "certeza-mao-na-mao", "chewing-gun-with-banana", "chiclete-com-banana", "chiquinho-azevedo", "choro-de-crianca", "chororo", "chuck-berry-fields-forever", "chuck-berry-fields-forever-ingles", "chuva-miuda", "cibernetica", "cidade-do-salvador", "cinema-novo", "ciranda", "cliche-do-cliche", "coincidencia", "com-medo-com-pedro", "com-que-roupa", "comunida", "comunidaria", "copacabana", "copo-vazio", "coracoes-a-mil", "coragem-pra-suportar", "cores-vivas", "corintia", "corisco", "could-you-be-loved", "crazy-pop-rock", "cultura-e-civilizacao", "dada", "danca-da-moda", "danca-de-shiva", "de-leve-get-back", "de-onde-vem-o-baiao", "deixar-voce", "desafinado", "desde-que-o-samba-e-samba", "despedida-de-solteira", "dinamarca", "divino-maravilhoso", "doce-carnaval-candy-all", "doente-morena", "doida-por-uma-folia", "dom-de-iludir", "domingo-no-parque", "domingou", "dona-desta-cancao", "dono-do-pedaco", "doralice", "dos-pes-a-cabeca", "drao", "duas-sanfonas", "duplo-sentido", "e", "e-luxo-so", "e-menina", "e-povo-e", "easy-skankin", "edyth-cooper", "ela", "ela-poeira", "ele-e-eu", "ele-falava-nisso-todo-dia", "eleve-se-alto-ao-ceulively-up-yourself", "ensaio-geral", "entao-vale-a-pena", "entre-a-sola-e-o-salto", "era-nova", "escurinho", "esoterico", "esperando-na-janela", "essa-e-pra-tocar-no-radio", "esses-mocos-pobres-mocos", "esta-na-cara-esta-na-cura", "estrela", "estrela-part-juliette", "estrela-azul-do-ceu", "eu-descobri", "eu-e-ela-estavamos-ali-encostados-na-parede", "eu-preciso-aprender-a-so-ser", "eu-sambo-mesmo", "eu-so-quero-um-xodo", "eu-te-dei-meu-ane", "eu-vim-da-bahia", "expresso-2222", "extra", "extra-ii-o-rock-do-seguranca", "falso-toureiro", "fe-menino", "fe-na-festa", "febril", "fechado-pra-balanco", "feliz-por-um-triz", "figura-de-retorica", "filhos-de-gandhi", "flora", "fogo-liquido", "formosa", "frevo-rasgado", "funk-se-quem-puder", "futurivel", "gaivota", "ganga-zumba-o-poder-da-bugiganga", "garota-de-ipanema", "geleia-geral", "gilbertos", "glasses", "graca-divina", "gueixa-no-tatame", "guerra-santa", "haiti", "here-and-now", "hino-da-figa", "hoje-o-dia-nasceu-diferente", "homem-de-neandertal", "iansa", "iemanja", "ile-aye", "ilha-da-ilusao", "imagine", "in-the-hot-sun-of-a-christmas-day", "indigo-blue", "iniciatica", "is-this-love", "jacintho", "jeca-total", "jingle-do-gloob", "joao-sabino", "joia-rara", "juazeiro", "jubiaba", "jurubeba", "kalil", "kao", "kaya-ngan-daya-kaya", "la-lune-de-goree", "la-renaissance-africaine", "la-vem-ela", "ladainha", "ladeira-da-preguica", "lady-neyde", "lamento-africano", "lamento-de-carnaval", "lamento-sertanejo", "lar-hospitalar", "lavagem-do-bonfim", "lente-do-amor", "lia", "lia-e-deia", "lick-samba", "lindinalva", "lindoneia", "lingua-do-pe", "loba-romana", "logos-versus-logo", "logunede", "louvacao", "luar-a-gente-precisa-ver-o-luar", "lugar-comum", "lunik-9", "luzia-luluza", "madalena", "malukete", "mamma", "mancada", "maquina-de-ritmo", "mar-de-copacabana", "maracatu-atomico", "marcha-da-tiete", "mardi-x-mars", "marginalia-2", "maria-me-perdoa-maria", "maria-me-perdoemaria", "maria-minha", "marina", "marmundo", "me-diga-moco", "meditacao", "meio-de-campo", "menina-do-sonho", "menina-goiaba", "metafora", "meteorum", "meu-amigo-meu-heroi", "meu-choro-pra-voce", "mico-preto", "milagre", "milho-verde", "minha-jovem-vizinha", "minha-princesa-cordel", "minha-senhora", "minimisterio", "misere-nobis", "mon-tiers-monde", "morena", "move-along-with-me", "mulher-de-coronel", "musa-cabocla", "musico-simples", "na-casa-dela", "na-real", "namba-a-gangamorada", "nao-chores-mais-no-woman-no-cry", "nao-grude-nao", "nao-tenho-medo-da-morte", "nao-tenho-medo-da-vida", "nascente-poente", "nega-photograph-blues", "neve-na-bahia", "nightingale", "no-ceu-da-vibracao", "no-dia-que-eu-vim-me-embora", "no-norte-da-saudade", "noite-de-lua-cheia", "norte-da-saudade", "nos-barracos-da-cidade-barracos", "nos-por-exemplo", "o-amor-daqui-de-casa", "o-bonde-sao-januario", "o-canto-da-ema", "o-cometa", "o-compositor", "o-eterno-deus-mu-danca", "o-fim-da-historia", "o-gandhi", "o-jornal", "o-livre-atirador-e-a-pegadora", "o-lugar-do-nosso-amor", "o-mar-e-o-lago", "o-oco-do-mundo", "o-pato", "o-relogio-quebrou", "o-revolver-do-meu-sonho", "o-rouxinol", "o-segundo-sol", "o-seu-amor", "o-som-da-pessoa", "o-sonho-acabou", "o-veado", "o-xote-das-meninas", "o-maria", "objeto-semi-identificado", "objeto-sim-objeto-nao", "odile-odila", "oia-eu-aqui-de-novo", "oju-oba", "ok-ok-ok", "olho-magico", "olho-nu", "onda-azul", "one-drop", "one-oclock-last-morning-20th-april-1970", "opachoro", "oracao-pela-libertacao-da-africa-do-sul", "oriente", "os-pais", "ouco", "outros-barbaros", "outros-viram", "pai-e-mae", "palco", "panis-et-circences", "parabolicamara", "parque-industrial", "patumbalacunde", "patuscada-de-gandhi", "pau-de-arara", "pe-da-roseira", "pe-quente-cabeca-fria", "pedacos-de-sinceridade", "pega-a-voga-cabeludo", "pela-graca-do-sol", "pela-internet", "pela-internet-2", "pessoa-nefasta", "pilula-de-alho", "planeta-dos-macacos", "plateia", "poco-fundo", "pode-waldir", "pop-wu-wei", "por-que-alguem-tem-inveja-de-voce", "positive-vibration", "pra-fazer-o-sol-nascer", "pra-que-mentir", "pratitude", "prece", "preciso-aprender-a-so-ser", "preciso-de-voce-nara-gil-part-gilberto-gil", "pretinha", "procissao", "procurando-tu", "pula-caminha", "punk-da-periferia", "quanta", "quarto-mundo", "quatro-pedacinhos", "que-besteira", "que-bom-prato-e-vatapa", "que-nem-jilo", "quem-mandou-pe-na-estrada", "queremos-guerra", "quero-ser-teu-funk", "questao-de-ordem", "quilombo-o-eldorado-negro", "rainha-do-mar", "rancho-da-boa-vinda", "rancho-da-rosa-encarnada", "rato-miudo", "realce", "rebel-music-3-oclock-road-block", "rebento", "refarm", "refavela", "refazenda", "refestanca", "refloresta", "rei-do-maracatu", "rep", "respeita-januario", "retidos-espirituais", "retirante", "retiros-espirituais", "rio-eu-te-amo", "roda", "roque-santeiro-o-rock", "rosa-morena", "saci-perere", "sai-do-sereno", "sala-do-som", "samba-de-los-angeles", "samba-do-aviao", "sampa", "sandra", "sao-joao-carioca", "sao-joao-xango-menino", "sarara-miolo", "sargento-pimenta-e-a-banda-solidao", "saudade-da-bahia", "se-ela-me-chamasse", "se-eu-quiser-falar-com-deus", "seamisai-sai-que-me-amavas-com-laura-pausini", "sebastian", "sei-que-me-amavas", "serafim", "sereno", "sete-silabas", "seu-olhar", "show-de-me-esqueci", "simples-desejo", "sina", "sitio-do-pica-pau-amarelo", "so-chamei-porque-te-amo", "sob-pressao", "sol-de-maria", "sonho-molhado", "soy-loco-por-ti-america", "stir-it-up", "super-homem-a-cancao", "table-tennis-table", "taj-mahal", "tartarugue", "tempo-rei", "tmpo-so-time-will-tell", "tenho-pena-de-quem-chora", "tenho-sede", "tenho-sede-2021", "terra-90", "testamento-do-padre-cicero", "the-green-giant-part-1", "the-three-mushrooms", "the-united-states-of-my-life", "them-belly-full-but-we-hungry", "three-little-birds", "tim-tim-por-tim-tim", "titicaca", "tiu-ru-ru", "toda-menina-baiana", "todo-dia-de-manha", "torpedo", "touche-pas-a-mon-pote", "tradicao", "tres-caravelas-las-tres-carabelas", "treze-de-dezembro", "trovoada", "turn-your-lights-down-low", "ultimo-pau-de-arara", "um-abraco-no-joao", "um-carro-de-boi-dourado", "um-samba", "um-sonho", "uma-coisa-bonitinha-part-joao-donato", "umeboshi", "vamos-fugir", "vamos-passear-no-astral", "vem-morena", "vem-menina", "vendedor-de-carangueijo", "vento-de-maio", "vi-ouvi", "vinte-e-seis", "violentidao", "viramundo", "vitrines", "voce-e-eu", "voce-e-voce", "volks-volkswagen-blue", "volks-volkswagen-blues-ingles", "volta-ao-mundo", "vou-me-embora-pra-pasargada", "waiting-in-vain", "what-a-wonderful-world", "xote", "ya-olokum", "yamandu-part-yamandu-costa", "zabele", "zoilogico", "zumbi", "zumbi-a-felicidade-guerreira"]}}, "Forró": {"Jackson do Pandeiro": {"url": "jackson-do-pandeiro", "discography": ["17-na-corrente", "1x1", "a-base-de-bala", "a-cadeira-do-rei", "a-mulher-do-anibal", "a-mulher-que-virou-homem", "a-onda-passou", "a-ordem-e-samba", "a-saudade-doi", "a-taca-era-dela", "a-vida-dos-outros", "acenderam-a-fogueira", "agua-com-leite", "ai-tertulina", "alegria-do-vaqueiro", "alegria-minha-gente", "alo-campina-grande", "amigo-do-norte", "amor-de-mentirinha", "aquele-pe-de-pitomba", "aqui-to-eu", "aquilo-bom", "b-a-ba", "baba-de-cachorro", "babalao", "baiao-do-bambole", "balancarama-a-roseira", "balanco-de-maria", "bodocongo", "boi-tungao", "bola-de-pe-em-pe", "brasilia-homenagem-a-construcao-de-brasilia-jk", "bumba-meu-boi", "cabo-tenorio", "cacugaruque", "cajueiro", "canoeiro-novo", "cantiga-da-perua", "cantiga-de-sapo", "capoeira-mata-um", "carrero", "casaca-de-couro", "catirina", "chiclete-com-banana", "chico-chora", "chu-chu-beleza", "chuchu-beleza", "chuvao", "coco-de-improviso", "coco-do-norte", "coco-social", "comigo-nao", "como-tem-ze-na-paraiba", "competente-demais", "coracao-bateu", "coracao-velho", "cremilda", "cumpadre-joao", "da-eu-pra-ela", "da-licenca", "de-pe-no-chao", "desconfianca", "direitos-iguais", "dr-boticario", "e-de-lei", "ele-disse", "empatou", "entra-na-roda", "eta-baiao", "eu-e-dona-maria", "eu-nao-vou-chorar", "eu-vim-de-longe", "eu-vou-pra-la", "falsa-patroa", "falso-toureiro", "feito-manteiga", "filomena-e-fedegoso", "fole-remendado", "forro-de-ze-lagoa", "forro-do-ze-lagoa", "forro-em-campina", "forro-em-caruaru", "forro-em-casa-amarela", "forro-em-limoeiro", "forro-na-gafieira", "forro-quentinho", "forrobodo", "garoto-de-cacule", "ginga-da-mulata", "heranca-de-meu-pai", "jacare-bebeu", "jaragua", "la-vai-a-boiada", "lamento-cego", "lei-da-compensacao", "liberdade-demais", "licao-de-tabuada", "madalena", "mae-solteira", "mane-gardino", "mania-de-mangar", "maria-da-pa-virada", "maria-do-anga", "meu-enxoval", "meu-passarinho-fugiu", "meu-patrao", "microbio-do-frevo", "morena-bela", "moxoto", "mulher-do-anibal", "mulher-malvada", "mundo-cao", "mundo-de-paz-e-amor", "mundo-novo", "na-base-da-chinela", "nao-me-falta-nada", "nao-sou-sapateiro", "nao-vou-chorar", "naquela-base", "nem-o-banco-do-brasil", "nem-vem-que-nao-tem", "no-quebradinho", "nortista-quatrocentao", "nosso-amor", "o-bom-torcedor", "o-canto-da-ema", "o-crime-nao-compensa", "o-curandeiro", "o-desordeiro", "o-dono-do-morro", "o-morro-cai", "o-navio-ta-bom-na-marcha", "o-pai-da-gabriela", "o-pau-rolou", "o-protetor", "o-puxa-saco", "o-rei-pele", "o-samba-e-o-pandeiro", "o-samba-melhorou", "o-solteirao", "papai-vai-de-trem", "passarinho-abandonado", "passaro-bacural", "passaro-bacurau", "passe-na-lapa", "peneirou-gaviao", "penerou-gaviao", "pinicapau", "pombo-correio", "praia-do-janga", "proibido-no-forro", "quadro-negro", "quebra-galho", "queima-do-judas", "quem-tem-um-nao-tem-nenhum", "quem-ve-cara-nao-ve-coracao", "quero-aprender", "quero-sambar", "rainha-de-tamba", "ralabucho", "rodopio", "rojao-de-brasilia", "rosa", "sabidinha", "saia-rota", "samambaia-trepadeira", "samba-do-birim-bim-bim", "samba-do-ziriguidum", "sambalancar", "sanfona-braba", "sao-joao-na-roca", "sao-joao-no-brejo", "sao-tome", "sebastiana", "secretaria-do-diabo", "secretario-do-diabo", "seguro-morreu-de-velho", "sem-cabeca", "semente-do-bem", "sete-meninas", "sina-de-cigarra", "ta-roendo", "tapa-na-boca-da-noite", "tarima", "tem-mulher-to-la", "todos-os-santos", "tres-pedidos", "tumtumtum", "twist-nao", "urubu", "vai-levando", "vamos-chegar-pra-la", "vamos-saculejar", "velho-sapeca", "verdadeiro-amor", "vespera-e-dia-de-sao-joao", "vila-mariana", "viola-no-frevo", "viva-sao-joao", "voce-e-eu", "voce-ja-era", "vou-de-tutano", "vou-gargalhar", "vou-me-casar", "xexeu-de-bananeira", "xodo-de-motorista", "xodo-no-forro", "chote-de-copacabana"]}, "Luiz Gonzaga": {"url": "luiz-gonzaga", "discography": ["17-legua-e-meia", "3-x-4-marilu", "a-cancao-do-carteiro", "a-carta", "a-cheia-de-24", "a-danca-da-moda", "a-danca-do-nicodemus", "a-feira-de-caruaru", "a-festa-do-milho", "a-letra-i", "a-ligeira", "a-moda-da-mula-preta", "a-moda-da-mula-preta-lorota-boa", "a-morte-do-meu-avo", "a-morte-do-vaqueiro", "a-mulher-do-meu-patrao", "a-mulher-do-sanfoneiro", "a-noite-e-de-sao-joao", "a-nova-jerusalem", "a-peleja-do-gonzagao-x-teo-azevedo", "a-puxada", "a-rede-veia", "a-sorte-e-cega", "a-triste-partida", "a-vida-do-viajante", "a-volta-da-asa-branca", "abc-do-sertao", "aboio-apaixonado", "acacia-amarela", "acaua", "acordo-as-quatro", "acucena-cheirosa", "adeus-a-januario", "adeus-iracema", "adeus-pernambuco", "adeus-rio", "ai-amor", "ai-tem", "ainda-e-noite-de-sao-joao", "alegria-de-pe-de-serra", "algodao", "alma-do-sertao", "alvorada-nordestina", "amanha-eu-vou", "amei-a-toa", "amigo-velho", "amor-da-minha-vida", "ana-rosa", "apelo-ao-soberano", "apologia-ao-jumento", "aproveita-gente", "aquarela-nordestina", "aquilo-bom", "aquilo-sim-que-vidao", "arcoverde-meu", "aroeira", "as-noites-de-junho-de-antigamente", "asa-branca", "asa-branca-traduccion", "asa-branca-volta-da-asa-branca", "asas-da-ilusao", "assum-preto", "ave-maria-sertaneja", "baiao", "baiao-agrario", "baiao-da-garoa", "baiao-da-penha", "baiao-de-dois", "baiao-de-sao-sebastiao", "baiao-dos-namorados", "baiao-gra-fino", "baiao-granfino", "baiao-polinario", "balaio", "balaio-do-veremundo", "balanca-a-rede", "balance-eu", "balanco-do-calango", "baldrama-macia", "bamboleado", "bandeira-dois", "bandinha-de-fe", "beata-mocinha", "benca-mae", "bicho-eu-vou-voltar", "bie-bie-brasil", "boca-de-caieira", "boca-de-forno", "bodocongo", "boi-bumba", "boiadeiro-2", "boiadeiro-cigarro-de-paia", "bom-pra-eu", "bom-pra-uns", "braia-dengosa", "buraco-de-tatu", "cabeca-inchada", "cabocleando", "caboclo-nordestino", "cabra-da-peste", "cacimba-nova", "cafe", "cajueiro-velho", "calango-da-lacraia", "caminhos-do-coracao", "cana-so-de-pernambuco", "canaa", "canana", "cantarino", "cantei", "cantiga-de-vem-vem", "canto-do-povo", "canto-do-sabia", "canto-sem-protesto", "capim-novo", "capital-do-agreste-caruaru", "capitao-jagunco", "carapeba", "cartao-de-natal", "casa-de-caboclo", "casamento-atrapaiado", "casamento-improvisado", "cavalo-crioulo", "cego-aderaldo", "cha-cutuba", "xamego", "chapeu-de-couro-e-gratidao", "chico-valente", "chofer-de-praca", "chorei-chorao", "choromingo", "chuculatera", "cidadao", "cidadao-de-caruaru", "cidadao-sertanejo", "cigarro-de-palha", "cintura-fina", "cirandeiro", "coco-xeem", "cocota", "comecaria-tudo-outra-vez", "comicio-do-mato", "contrastes-de-varzea-alegre", "conversa-de-barbeiro", "coracao-molim", "cordel", "coronel-pedro-do-norte", "corrida-de-mourao", "corridinho-caninde", "cortando-o-pano", "crepusculo-sertanejo", "creuza-morena", "da-licenca-pra-mais-um", "danado-de-bom", "danca-do-capile", "danca-mariquinha", "daquele-jeito", "de-fia-pavi", "de-juazeiro-a-crato", "de-olho-no-candeeiro", "de-teresina-a-sao-luis", "dedo-mindinho", "deixa-a-tanga-voar", "deixe-o-rio-desaguar", "dengo-maior", "depois-da-derradeira", "derramaro-o-gai", "desessete-legua-e-meia", "despedida", "desse-jeito-sim", "dezessete-e-setecentos", "dia-de-sao-joao", "dia-dos-pais", "diz-que-vai-virar", "do-lado-que-relampeia", "documento-de-matuto", "dona-vera-tricotando", "doutor-do-baiao", "e-sem-querer", "e-sempre-assim", "engabelando", "engenho-massangana", "erosao", "erva-rasteira", "espere-por-mim", "estrada-de-caninde", "estrela-de-ouro", "eterno-cantador", "eu-e-meu-fole", "eu-e-minha-branca", "eu-me-enrabicho", "eu-so-quero-um-xodo", "eu-vou-cortando", "eu-vou-pro-crato", "faca-isso-nao", "facilita", "farinhada", "feijao-cum-cove", "feira-de-caruaru", "festa", "festa-de-santo-antonio", "festa-napolitana", "festa-no-ceu", "fica-mal-com-deus", "firim-firim-firim", "flor-do-lirio", "fogo-do-parana", "fogo-sem-fuzil", "fogo-pagou", "fogueira-de-sao-joao", "fole-danado", "fole-gemedor", "forro-da-miadeira", "forro-das-criancas", "forro-de-cabo-a-rabo", "forro-de-caruaru", "forro-de-mane-vito", "forro-de-ouricuri", "forro-de-pedro-chaves", "forro-de-ze-antao", "forro-de-ze-buchudo", "forro-de-ze-do-baile", "forro-do-bom", "forro-do-ze-antao", "forro-fungado", "forro-gostoso", "forro-no-escuro", "forro-no-interior-furum-furum-firim", "forro-numero-1", "frei-damiao", "frescobol", "from-united-states-of-piaui", "fruta-madura", "frutos-da-terra", "fulo-da-maravilha", "fulo-maravilha", "galo-garnize", "garimpeiro-sonhador", "garota-todeschini", "gato-angora", "gibao-de-couro", "guerreiro-menino", "homenagem-a-ze-dantas", "hora-do-adeus", "imbalanca", "indiferente", "ja-era-tempo", "ja-vou-mae", "januario", "januario-vai-tocar", "jardim-da-saudade", "jesus-sertanejo", "juazeiro", "juca", "juvina", "karolina-com-k", "la-vai-pitomba", "ladrao-de-bode", "lampiao-era-besta-nao", "lampiao-falou", "lascando-o-cano", "legua-tirana", "lembranca-da-primavera", "lenda-de-sao-joao", "lendas-de-sao-joao", "lenha-verde", "linda-brejera", "lorota-boa", "louvacao-a-joao-xxiii", "luar-do-sertao", "lula-meu-filho", "lulu-vaqueiro", "macapa", "maceio", "madame-baiao", "madruceu-o-milho", "malhada-dos-bois", "mamulengo", "manduquinha", "mane-e-zabe", "mane-gamba", "mangaratiba", "manoelito-cidadao", "marabaixo", "marcha-da-petrobras", "maria", "maria-baiana", "maria-cangaceira", "mariana", "marimbondo", "matuto-aperreado", "matuto-de-opiniao", "mazurca", "me-afubelo", "menestrel-do-sol", "menino-do-bracana", "meu-araripe", "meu-chevrolet", "meu-dedo-mindinho", "meu-padrim", "meu-pajeu", "minha-ful", "moca-de-feira", "moda-da-mula-preta", "moela-e-coracao", "morena-bela", "morena-cor-de-canela", "moreninha-tentacao", "moreninha-moreninha", "motivacao-nordestina", "mulher-de-hoje", "na-cabana-do-rei", "na-emenda", "na-lagoa-do-amor", "nao-bate-nele", "nao-e-so-a-paraiba-que-tem-ze", "nao-foi-surpresa", "nao-vendo-nem-troco", "nega-zefa", "nem-se-despediu-de-mim", "nessa-estrada-da-vida", "no-canto-do-salao", "no-ceara-nao-tem-disso-nao", "no-dia-em-que-eu-vim-embora", "no-meu-pe-de-serra", "no-pianco", "noites-brasileiras", "nordeste-pra-frente", "nordeste-sangrento", "nos-cafundo-de-bodoco", "numa-sala-de-reboco", "nunca-mais-vi-esperanca", "o-adeus-da-asa-branca-tributo-a-humberto-teixeira", "o-andarilho", "o-baiao-vai", "o-cacador", "o-cantador", "o-casamento-da-rosa", "o-cheiro-da-carolina", "o-coreto-da-pracinha", "o-delegado-no-coco", "o-festao", "o-fole-roncou", "o-homem-da-terra", "o-maior-tocador-seu-januario", "o-manganga", "o-milagre", "o-mote-maquinista-e-sacristao", "o-papa-e-o-jegue", "o-passo-da-rancheira", "o-resto-a-gente-ajeita", "o-tocador-quer-beber", "o-torrado", "o-torrado-da-lili", "o-urubu-e-um-triste", "o-veio-macho", "o-vovo-do-baiao", "o-xamego-da-guiomar", "o-xote-das-meninas", "obrigado-joao-paulo", "oia-eu-aqui-de-novo", "oito-e-dois-dez", "olha-a-pisada", "olha-pro-ceu", "onde-o-nordeste-garoa", "onde-tu-ta-nenem", "orelia", "os-bacamarteiros", "os-olhinhos-do-menino", "ou-casa-ou-morre", "outro-amanha-sera", "ovo-azul", "ovo-de-codorna", "padre-sertanejo", "padroeira-do-brasil", "pagode-russo", "pai-nosso", "palavras-ao-vento", "pao-duro", "paraiba", "paraxaxa", "passaro-carao", "passo-do-pinguim", "passo-fome-mas-nao-deixo", "pau-de-arara", "pau-de-sebo", "paulo-afonso", "pedaco-de-alagoas", "pedacos-de-alagoas", "pedido-a-sao-joao", "penas-do-tie", "penero-xerem", "pense-neu", "perpetua", "pesqueira-centenaria", "petrolina-juazeiro", "piaui", "piriri", "pisa-no-pilao", "plano-piloto", "pobre-do-sanfoneiro", "pobreza-por-pobreza", "portador-do-amor", "pra-frente-goias", "pra-nao-morrer-de-tristeza", "pra-onde-tu-vai-baiao", "pra-que-mais-mulher", "prece-por-exu-novo", "procissao", "projeto-asa-branca", "pronde-tu-vai-lui", "propria", "quadrilha-chorona", "quarque-dia", "quase-maluco", "que-modelos-sao-os-seus", "que-nem-jilo", "queimando-lenha", "queixas-do-norte", "quer-ir-mais-eu", "quero-cha", "quero-uma-mulher", "quero-ver", "quero-ver-correr-moleque", "rainha-do-mundo", "ranchinho-de-paia", "raparam-tudo", "razao-do-meu-querer", "recado-do-velho", "regresso-do-rei", "rei-bantu", "relogio-baiao", "respeita-do-navio-riacho-do-navio-forro-no-escuro", "respeita-januario", "retrato-de-um-forro", "riacho-do-navio", "riacho-do-navio-forro-no-escuro", "rio-brigida", "rodovia-asa-branca", "roendo-unha", "romance-matuto", "rosa-de-mearim", "rosinha", "sabia", "salmo-dos-aflitos", "samarica-parteira", "sanfona-do-povo", "sanfona-sentida", "sanfoneiro-macho", "sanfoneiro-ze-tatu", "sanfoninha-choradeira", "sangrando", "sangue-do-nordestino", "santana", "santo-antonio-nunca-casou", "sao-francisco-de-caninde", "sao-joao-antigo", "sao-joao-chegou", "sao-joao-do-carneirinho", "sao-joao-na-roca", "sao-joao-nas-capita", "sao-joao-no-arraia", "sao-joao-sem-futrica", "saudade-da-boa-terra", "saudade-de-pernambuco", "saudade-do-velho", "saudade-doi", "saudades-de-helena", "se-nao-fosse-esse-meu-fole", "sebastiana", "sequei-os-olhos", "serena-do-mar", "serido", "serrote-agudo", "sertanejo-do-norte", "sertao-de-aco", "sertao-setenta", "sertao-sofredor", "sete-faces", "siri-jogando-bola", "so-vale-quem-tem", "so-xote", "sorriso-cativante", "sou-do-banco", "suplica-cearense", "ta-bom-demais", "ta-qui-pa-tu", "tacaca", "tambau", "tamborete-de-forro", "tamborete-forro", "tei-tei-arraia", "tei-tei-no-arraia", "tenho-onde-morar", "terra-vida-e-esperanca", "tesouro-e-meio", "testamento-de-caboclo", "tic-tac-tic-tac", "to-sobranco", "to-sobrando", "toca-pai", "toca-uma-polquinha", "todo-homem-quer", "toque-de-rancho", "tres-e-trezentos", "tristeza-do-jeca", "tropeiros-da-borborema", "tu-que-mingabela", "ultimo-pau-de-arara", "uma-pra-mim-outra-pra-tu", "uma-pra-mim-uma-pra-tu", "umbuzeiro-a-saudade", "vaca-estrela-e-boi-fuba", "valha-deus-senhor-sao-bento", "vamos-ajuntar-os-trocos", "vamos-chegando-pra-la", "vamos-xaxear", "vaqueiro-veio", "vassouras", "ve-se-ligas-para-mim", "velho-novo-exu", "velho-pescador", "vem-morena", "vida-de-vaqueiro", "vida-de-viajante", "vida-ruim", "viola-de-penedo", "vitoria-de-santo-antao", "viva-meu-padim", "viva-o-arigo", "viva-o-rei", "vo-casa-ja", "vou-mudar-de-couro", "vou-te-matar-de-cheiro", "vovo-do-baiao", "vozes-da-seca", "xamego-2", "xanduzinha", "xaxado", "xeem", "xengo", "xo-pavao", "xote-das-meninas", "xote-das-mocas", "xote-do-saoite", "xote-do-veio", "xote-dos-cabeludos", "xote-ecologico", "xote-machucador", "ze-budega", "ze-dantas", "ze-matuto"]}, "Flávio José": {"url": "flavio-jose", "discography": ["a-casa-da-saudade", "a-dama-e-o-pintor", "a-dor-da-separacao", "a-forca-da-paixao", "a-natureza-das-coisas", "a-poeira-e-a-estrada", "a-procura-de-um-amor", "a-vida-e-voce", "abc-do-amor-a-separacao-lembranca-de-voce", "amor-de-verdade", "amor-sem-preconceito", "anjo-malandrinho", "anjo-querubim", "apaixonado-por-voce", "asas-da-ilusao", "avoante", "balancando-a-tanajura", "bebe-chorao", "beijo-doce", "bola-de-neve", "brasas", "brasilidade", "brincando-de-solidao", "caboclo-sonhador", "cabresto", "cade-voce", "caia-por-cima-de-mim", "caminhos-do-sertao", "cancao-da-saudade", "carencia", "cartinha-pra-seu-luis", "casa-velha-abandonada", "casa-velha-de-sape", "cheiro-de-forro", "cheiro-de-terra-molhada", "chuva", "cicatriz", "cidadao-comum", "cidade-grande", "como-falar-de-flor", "como-vai-voce", "companheira", "coracao-que-ama", "danca-da-vida", "de-mala-e-cuia", "deixe-o-rio-desaguar", "devolva", "dialogo", "dificil-demais", "disfarce", "dois-rubis", "dom-cristalino", "e-sempre-assim", "e-so-saudade", "endoideceu-meu-coracao", "engenho-velho", "enxugando-gelo", "espumas-ao-vento", "estradar", "eu-ja-vi-tudo", "eu-nao-preciso-de-voce", "eu-sou-o-forro", "eu-te-amo", "festa-do-vaqueiro", "festejos-de-beija-flor", "filho-do-dono", "filosofia", "fomos-feitos-um-para-o-outro", "forro-da-tremedeira", "forro-maneiro", "frutificando", "fulo-do-campo", "fuxico", "gente-sofrida", "heroi-do-meu-sertao", "incerteza", "ja-nao-conserto-mais", "jogo-limpo", "juntando-os-trocos", "lembranca", "lembranca-de-um-beijo", "louco-de-paixao", "mae", "mansa-demais", "mar-de-desejo", "me-diz-amor", "me-diz-amor-2", "menina-mansa", "menino-chorao", "mensageiro-beija-flor", "meu-cenario", "meu-coco-tem", "meu-siria", "meu-xamego-meu-xodo", "minha-mae", "minha-prenda", "moinho-dagua", "mulher-comprometida", "na-cacimba-do-amor", "na-quentura-do-forro", "nao-me-deixe", "nao-podia-ser-melhor", "neguinha", "nordestino-lutador", "nos-terreiros-do-forro", "novilha-rainha", "o-berco-da-minha-paz", "o-bom-do-amor", "o-meu-direito", "o-meu-jeito-de-amar", "o-meu-pais", "o-mundo-nao-perdoa", "o-poeta-cantador", "o-preco-da-saudade", "o-que-a-gente-faz", "o-rei-nas-estrelas", "o-rei-da-garapa", "o-tempo-e-a-seca", "oh-vaqueiro", "orguho-de-ser-nordestino", "orgulho-de-ser-nordestino", "paixao-escondida", "paixao-tirana", "palavras-ao-vento", "pano-de-chao", "papel-de-confeito", "pe-na-estrada", "pedido-a-sao-joao", "pimenta-no-salao", "pobre-matuto", "povo-de-gado", "pra-amar-e-ser-feliz", "pra-gente-se-divertir", "pra-que-dividir-2", "pra-que-dividir", "pra-que-solidao", "pra-todo-mundo", "pra-ver-o-amor-nascer", "pra-voce-voltar-pra-mim", "puxando-o-fole", "quadrado-feito-uma-rapadura", "quando-bate-o-coracao", "quando-o-amor-acontece", "quando-olho-pra-voce", "que-nem-vem", "que-te-faco-gamar", "queima-fogueira", "qui-nem-gilo", "raiz-do-coracao", "recado", "represa-do-querer", "respeito-e-bom-e-eu-gosto", "ressentimento", "retalhos-de-paixao", "romance-capenga", "sangue-nordestino", "sao-joao-la-na-bahia", "sao-joao-no-municipal", "saudade-da-boa", "se-der", "seca-nordestina", "seducao", "segura-o-chororo", "sem-destino-e-sem-concerto", "sem-ferrolho-e-sem-tramela", "sem-nao-nem-talvez", "sem-ver-voce", "sem-vergonheira", "sertao", "seu-olhar-nao-mente", "so-confio-em-tu", "so-falta-voce-voltar", "so-o-tempo-quem-vai-dizer", "so-um-dedinho-ou-um-golinho", "sobras-de-um-amor", "ta-bom-que-ta-danado", "tao-sozinho", "tareco-e-mariola", "tem-arrasta-pe", "tem-que-ser-forro", "tem-que-ser-pra-ser", "tempo-de-menino", "temporal-de-saudade", "tempos-de-crianca", "tenho-muito-amor-pra-dar", "terra-prometida", "toalha-de-prazer", "tonha", "tudo-mudou", "um-passarinho", "um-verdadeiro-amor", "utopia-sertaneja", "va-embora", "vaqueiro-violeiro", "velho-ipojuca", "vendavais", "vida-boa-aperriada", "voce-na-minha-vida", "vou-rifar-meu-coracao", "xote-brasileiro"]}, "Dominguinhos": {"url": "dominguinhos", "discography": ["17-legua-e-meia", "a-banda", "a-costureira", "a-lavadeira", "a-magia-do-olhar", "a-moca-do-metro", "a-procura-de-forro", "a-quadrilha-instrumental", "a-sede-do-rio-a-fome-do-pao", "a-semana", "a-verdade-doi", "abri-a-porta", "acacia-amarela", "ainda-acho-pouco", "alegria-de-pe-de-serra", "alem-da-ultima-estrela", "amigo-velho-tocador", "amizade-sincera", "amor-ingrato", "anjo-da-guarda", "anjo-querubim", "arrasta-pe", "arrebol", "as-mocas-de-angical", "assum-preto", "baiao", "baiao-cacula", "balanca-sanfoneiro", "bateu-no-coracao", "bem-querer", "benca-mae", "bota-severina-pra-moer", "briga-a-toa", "brincadeira-de-rua", "cai-fora", "caminhoneiro", "caminhos-do-mar", "canta-luiz", "canto-nordestino", "capim-novo", "carece-de-explicacao", "carinho-gostoso", "casa-grande", "casa-tudo-azul", "casa-comida-e-paixao", "casamento-no-juazeiro", "castanhao", "catingueira-fulorou", "caxinguele", "chama", "chameguinho", "chega-morena", "chegando-de-mansinho", "cheguei-pra-ficar", "cintura-de-abelha", "coco-da-bahia", "coisa-linda", "coisa-muito-fina", "com-o-pe-no-forro", "como-eu-sou", "como-tudo-comecou", "conterraneos", "contrato-de-separacao", "corre-pelo-coracao", "danado-no-forro", "dancador-ruim", "de-amor-eu-morrerei", "de-mala-e-cuia", "de-onde-vem-o-baiao", "de-pe-no-chao", "de-volta-pro-aconchego", "dedicado-a-voce", "depois-da-derradeira", "derramaro-o-gai", "desilusao", "detras-do-meu-quintal", "diz-amiga", "doidinha-pra-dancar", "doidinho-pra-ver", "doidinho-doidinho", "duas-frutinhas", "duvide-o-do", "e-tradicao", "e-voce", "eita-paraiba", "esse-brasil-e-meu", "esse-velho-sol", "estacao", "estrela-gonzaga", "estrela-somos-nos", "estrelas-somos-nos", "eu-chego-cedo", "eu-me-lembro", "eu-so-quero-um-xodo", "eu-sou-do-banco", "eu-sou-do-mundo", "eu-vou-de-banda", "fala-coracao", "faz-de-mim", "feira-de-mangaio", "festa-em-olinda", "firim-fim-fom-do-fole", "flor-de-maracuja", "fogo-de-amar", "fogo-e-gasolina", "fogo-na-paia", "forro-arretado", "forro-brasileiro", "forro-do-jesuino", "forro-do-massape", "forro-do-quem-quer", "forro-do-sapateiro", "forro-em-ribeirao", "forro-energia", "forro-no-escuro", "forro-no-sertao", "forro-reveillon", "forro-tracado", "forrozao", "forrozeiro-apaixonado", "forrozinho-bom", "fulo-de-araca", "galope-do-desejo", "gandaeira", "gaviao-peneirador", "gonzaga-coracao", "gostoso-demais", "gotas-de-prata", "historia-de-contador", "hoje-e-dia-de-forro", "homenagem-a-lindu", "ilusao", "ingratidao", "isso-aqui-ta-bom-demais", "ja-vi-tudo", "ja-vou-mae", "judiou-sem-razao", "kid-lampiao-com-cesar-menotti-e-fabiano", "lamento-sertanejo", "lembrando-de-voce", "lisbela", "luciana", "luz-do-candeeiro", "maceio", "mais-que-um-amigo", "maravilhoso-sao-joao", "me-pede-um-carinho", "meu-amor-quem-dera", "meu-pajeu", "meu-piao", "minha-ilusao", "minha-pequena", "minha-vida-e-te-amar", "minha-vidinha", "minhas-desculpas", "moca-de-feira", "morena-bonita", "motorista-brasileiro", "nao-faz-assim", "nao-ha-compreencao", "nao-me-faca-surpresa", "nao-prende-minhas-asas", "nao-quero-saber-de-crise", "nao-sai-de-perto-de-mim", "nao-tem-jeito-que-de-jeito", "nas-costas-do-brasil", "nem-me-deu-bola", "nem-pra-tu-nem-pra-eu", "nem-santo-nem-ouro", "nem-se-despediu-de-mim", "ninguem-e-demais", "ninguem-vai-nos-separar", "no-dia-em-que-eu-vim-me-embora", "no-forro-de-dona-zefa", "no-puladinho", "nossas-ultimas-viagens", "numa-sala-de-reboco", "o-amor-eu-encontrei", "o-babulina", "o-canto-de-acaua", "o-cheiro-puro-deste-chao", "o-cortador-de-cana", "o-galo-ja-miudou", "o-gosto-do-meu-amor", "o-juazeiro-e-a-sombra", "o-mel-e-o-fel", "o-menina-chega-ca", "o-no", "o-pavio-e-o-lampiao", "o-que-aconteceu-menina", "o-riacho-do-imbuzero", "o-sertao-te-espera", "o-trinado-do-trovao", "o-vendedor-de-caranguejo", "o-xara", "oceano-do-querer", "ocultei", "oi-la-vou-eu", "oi-que-balanco-bom", "olha-pro-ceu", "onde-esta-voce", "os-quindins-de-iaia", "para-boi-dormir", "peba-na-pimenta", "pedras-que-cantam", "pele-macia-cor-morena", "penitente", "pensando-nela", "petrolina-juazeiro", "plantio-de-amor", "pode-morrer-nessa-janela", "pois-e", "ponto-fraco", "por-amor-ao-forro", "pra-desabafar", "pra-eu-e-tu", "pra-fungar-e-poeirar", "pra-la-de-bom", "pra-se-misturar-gostoso", "prece-a-luiz", "preciso-do-teu-sorriso", "puxa-puxa-rala-coco", "quando-chega-o-verao", "quem-eras-tu", "quem-foi-que-viu", "quem-me-levara-sou-eu", "quero-nem-saber", "quero-um-chamego", "quero-ver-voce-feliz", "querubim", "rala-o-coco-lili", "rato-enfrentando-gato", "recem", "recife-minha-paixao", "remelexo", "represa-do-querer", "retrato-redondinho", "riacho-do-navio", "riso-cristalino", "roca-roca", "rolo-da-moenda", "sabia", "sai-do-sereno", "salao-de-barro-batido", "sanfona-do-povo", "sanfona-sentida", "saudade-matadeira", "se-lembra-coracao", "seja-como-flor", "sem-rumo-e-sem-prumo", "sem-saida", "sempre-voce", "sete-meninas", "seu-luis-e-sao-joao", "sia-mariquinha", "sorriso-cativante", "suplica-cearense", "tantas-palavras", "te-faco-um-cafune", "tempo-menino", "tempo-triste", "tenho-sede", "tentando-sobreviver", "ter-voce-e-ter-razao", "terra-da-procissao", "teu-carinho", "to-beirando", "to-indo-embora", "to-sozinho", "tudo-e-sao-joao", "um-aperto-de-mao", "um-lugar-ao-sol", "um-minuto-e-muito-tempo", "va-com-deus", "vai-ter-zoeira", "varios-caminhos", "veja", "vem-ficar-comigo", "vem-morena", "viajante", "voce-e-ouro", "voce-endoideceu-meu-coracao-com-oswaldir-e-carlos-magrao", "volta-e-meia", "vou-voltar", "voz-do-vento", "vozes-da-seca-com-elba-ramalho", "xote-da-gameleira", "xote-das-meninas", "xote-puladinho", "ze-do-rock"]}, "Sivuca": {"url": "sivuca", "discography": ["adeus-maria-fulo", "alagamar", "arapua-fazendo-mel", "asa-branca", "bailado", "cancao-que-se-imaginara", "cantador-latino", "cintura-fina", "conto-de-fadas", "em-cada-parte-em-cada-ponte", "estrela-guia", "feira-de-mangaio", "fogo-pagou", "forro-da-bicharada", "joao-e-maria", "macho-e-femea", "no-tempo-dos-quintais", "novas-cancoes", "onca-caetana", "os-meninos-da-mangueira", "pro-que-der-e-vier", "te-pego-na-mentira"]}}, "Samba": {"Cartola": {"url": "cartola", "discography": ["a-cancao-de-saudade", "a-cancao-que-chegou", "a-cor-da-esperanca", "acontece", "aconteceu", "alegria", "alvorada", "amor-proibido", "ao-amanhecer", "as-rosas-nao-falam", "assim-nao-da", "autonomia", "beijos", "bem-feito", "bobagem", "brasil-terra-adorada", "cadeira-vazia", "camarim", "cancao-de-saudade", "catedral-do-inferno", "chega-de-demanda", "ciencia-e-arte", "como-e-que-eu-posso", "consideracao", "corra-e-olhe-o-ceu", "de-me-gracas-senhora", "deixa-pra-la", "desfigurado", "disfarca-e-chora", "divina-dama", "dois-bicudos", "enquanto-deus-consentir", "ensaboa", "escurinha", "espero-por-ti", "estudei-demais", "feriado-na-roca", "festa-da-vinda", "fim-de-estrada", "fita-os-meus-olhos", "fiz-por-voce-o-que-pude", "grande-deus", "interroguei-uma-rosa", "labaredas", "leito-vazio", "mangueira", "maravilhoso-vagabundo", "mesma-estoria", "meu-drama-senhora-tentacao", "motivacao", "nao-faz-mal-amor", "nao-faz-amor", "nao-posso-viver-sem-ela", "nao-quebre-o-meu-tamborim", "nao-quero-mais-amar-a-ninguem", "nao-sei", "nos-dois", "o-inverno-do-meu-tempo", "o-mundo-e-um-moinho", "o-que-e-feito-de-voce", "o-samba-do-operario", "o-sol-nascera", "ordenes-e-farei", "partiu", "peito-vazio", "pouco-importa", "pranto-de-poeta", "preciso-me-encontrar", "que-sejam-bem-vindos", "quem-me-ve-sorrindo", "sala-de-recepcao", "sei-chorar", "senhora-tentacao", "senoes", "silencio-de-um-cipreste", "sim", "soldado-do-amor", "tempos-idos", "tive-sim", "tu-vais-ao-samba", "velho-estacio", "vem", "verde-que-te-quero-rosa", "vou-te-contar-tintim-por-tintim"]}, "Bezerra da Silva": {"url": "bezerra-da-silva", "discography": ["a-bandeira-do-acari", "a-carta", "a-coisa-mudou", "a-culpada-foi-quiteria", "a-fumaca-ja-subiu-pra-cuca", "a-giria-e-a-cultura-do-povo", "a-lei-do-morro", "a-macaca-vai-cantar", "a-necessidade", "a-rapa", "a-rasteira-do-presidente", "a-semente", "a-vaca-da-minha-sogra", "a-vida-do-povo", "achei-a-vida", "acordo-de-malandro", "acreditar-na-palavra", "alo-sao-pedro", "aos-donos-da-minha-nacao", "aos-donos-da-nacao", "apertar-o-cinto", "apolo-so-samba", "aqueles-morros", "arma-do-incompetente", "arruda-de-guine", "as-40-dps", "as-favelas-que-nao-exaltei", "asa-a-cobra", "assim-sim", "assino-embaixo-pela-minha-rapaziada-letras", "assombracao-de-barraco", "baixada", "bata-da-vovo", "bem-melhor-que-voce", "bicho-feroz", "boca-de-radar-letras", "bom-jesus-de-nazareno", "bom-jesus-nazareno", "brasa-por-cima-de-brasa", "pela-bruta-inveja-de-caim", "cabeca-pra-vovo", "cachorrinho-de-policia", "campo-minado", "candidato-cao-cao-letras", "canudo-de-ouro-letras", "cara-de-boi", "cara-de-cruel", "carne-de-pescoco", "casa-santa", "catatau-nervoso", "chave-do-milagre", "chico-chora", "chico-nao-deu-sorte", "chorao-de-aluguel", "cobra-criada", "coco-de-itambe", "coco-de-obrigacao", "coco-do-b", "coco-do-tato", "coco-do-trocadilho", "coisa-da-antiga", "coisa-ruim", "colina-maldita", "com-dinheiro-tudo-bem-letras", "compositores-de-verdade", "conselho-de-luz", "cuidado-com-o-bicho", "curumim", "da-pesada", "dando-mole-pra-kojak", "dava-dois", "dedo-duro", "defunt-caguete", "defunto-grampeado", "defunto-morto-nao-fala", "deixa-uma-paia-pro-veio-queima", "divino-mestre", "dois-venenos-juntos", "dona-maria-baiana", "doutores-do-meu-brasil", "e-esse-ai-que-e-o-homem", "e-ladrao-que-nao-acaba-mais", "e-o-bicho-e-o-bicho", "e-rabo-de-saia", "ele-cagueta-com-dedao-do-pe", "ele-nao-e-a-vossa-mas-e-o-papa", "em-seu-lar", "era-da-nova-tecnologia", "este-homem-e-inocente", "eu-andava-nas-trevas", "eu-nao-sou-santo", "eu-nao-tenho-culpa", "eu-nao-vou-pedir-maleme", "eu-senti", "eu-sou-favela", "eu-tiro-e-onda", "eu-to-de-pe", "feitico-do-tiao", "filho-de-mae-solteira", "filho-do-dono", "flamengo-e-mangueira", "fofoqueiro-e-a-imagem-do-cao", "foi-o-dr-delegado-que-disse", "foi-teu-olhar", "fui-obrigado-a-chorar", "garfo-no-bolso", "garoa", "garrafada-do-norte", "gato-com-bronca", "gente-fina", "grampeado-com-muita-moral", "homem-inocente", "ilha-grande", "inferno-colorido", "instinto-de-traira", "iolanda", "ipanema", "ja-falei-com-voce-letras", "ja-matei-os-meus-desejos", "ja-nasci-com-a-cabeca-feita", "ja-nasci-com-cabeca", "jogo-proibido", "juiz-de-toda-a-humanidade", "justica-social", "legitima-defesa", "levanta-a-cabeca", "lingua-de-tamandua", "lingua-grega", "lugar-macabro", "malandragem-da-um-tempo", "malandragem-maloca-o-flagrante", "malandro-consciente", "malandro-demais-vira-bicho", "malandro-e-malandro-e-mane-e-mane-letras", "malandro-moderno", "malandro-nao-vacila2", "malandro-rife", "medo-de-virar-galeto-letras", "mete-a-mao-que-tu-vai-ver", "meu-bem", "meu-bom-juiz", "meu-pai-e-general-de-umbanda", "meu-pirao-primeiro", "meu-samba-e-duro-na-queda", "minha-drogaria", "minha-sogra-parece-sapatao", "muamba", "mudo-caguete", "muita-responsabilidade", "mulambo-so", "mulher-sem-alma", "na-aba", "na-boca-do-mato", "na-hora-da-dura", "na-hora-da-verdade", "na-rocinha", "nao-e-conselho", "nao-ha-mais-jeito", "nao-tenho-lar", "nariz-de-bronze", "negro-de-verdade", "no-meu-barco", "nossos-irmaos", "noticia", "nunca-vi-ninguem-dar-dois-em-nada", "o-bagaco-da-laranja", "o-bom-baiano", "o-bom-pastor", "o-bom-sofredor", "o-cabrito-berrou", "o-catimbozeiro", "o-dr-esta-na-sua-capturacao", "o-federal", "o-filho-da-jurema", "o-juramento-e-o-meu-lugar", "o-juramento-jurou", "o-malandro-era-forte", "o-mane-so-fez-graca", "o-medo-de-ficar-pobre", "o-pinel", "o-poeta-operario", "o-preco-da-gloria", "o-preco-da-traicao", "o-preto-e-o-branco", "o-rei-da-cocada-preta", "o-rei-do-coco", "o-ricardao", "o-segundo-nazareno", "o-trapo", "o-vacilao", "olha-o-boi", "os-direitos-do-otario", "os-dps-de-sao-paulo", "os-federais-estao-te-filmando", "os-sambistas-brasileiros", "os-tres-pagodeiros-do-rio", "overdose-de-cocada-letras", "pagode-na-casa-do-gago", "pai-veio-171", "papo-de-malandro", "parabens-pra-voce-meu-brasil", "partideiro-indigesto", "partideiro-sem-no-na-garganta", "passa-o-rodo-nele", "pastor-trambiqueiro", "pega-eu", "pena-de-morte", "piranha", "pobre-aposentado", "pobre-compositor", "pode-acreditar-em-mim", "pour-la-madame", "povo-da-colina", "preconceito-de-cor", "prepara-o-pinote", "presepada-do-mane", "presidente-cara-de-pau", "prezepada", "produto-do-morro", "produto-importado", "q-g-do-samba", "quando-o-morcego-doar-sangue", "quem-fala-mal-de-mim-tem-despeito", "quem-usa-antena-e-televisao", "rabo-de-foguete", "raiva-de-tudo", "rapa-cuia", "redencao", "ressuscita-ele", "reuniao-de-bacana-se-gritar-pega-ladrao", "ricardao", "roubo-do-cabrito", "s-o-s-baixada", "safado-e-safado-mesmo", "samba-manifesto", "sao-murungar", "saudacao-as-favelas", "se-eu-nao-mato-eu-morro", "se-leonardo-da-vinte", "se-liga-doutor", "se-nao-avisar-o-bicho-pega", "se-nao-fosse-a-ajuda-da-rapaziada", "se-nao-fosse-o-samba", "se-tenho-razao", "segura-a-viola-ze-pilintra", "seja-o-que-deus-quiser", "semente", "senhor-doutor", "sequestraram-minha-sogra-letras", "sereia", "so-quando-morcego-doar-sangue", "so-via-faca-voar", "sobrou-caixao", "sombra-do-coqueiro", "sorte-e-sorte", "sou-cadeado", "sou-produto-do-morro", "sua-cabeca-nao-passa-na-porta", "taxistas-do-meu-brasil", "tem-coca-ai-na-geladeira", "terreiro-de-safado", "toda-noite-sonho", "todo-enrolado", "todo-errado", "todo-poderoso", "transacao-de-malandro", "trem-do-futuro", "tua-batata-ta-assando", "um-comedia-nas-paradas", "vai-chover-hoje-urubu", "vai-pagar-caro-informante", "valente-na-boca-do-boi", "vamo-simbora-nenem", "velha-demais", "vendo-que-era-bom", "veneno-de-peconha", "venenosas-serpentes", "venta-nervosa", "verdadeiro-canalha", "vestiu-saia-ta-pra-mim", "vida-de-operario", "vigia-sagas", "vinganca-cruel", "violencia-gera-violencia", "vitimas-da-sociedade", "viuva-de-seis", "vivo-que-nem-papel", "vizinha-faladeira", "voce-nao-gosta-de-voce", "vou-contar-ate-tres", "vou-lhe-dar-uma-colher", "vovo-cantou-pra-subir", "vovo-tira-tira", "ze-fofinho-de-ogum", "zebu"]}, "Vinicius de Moraes": {"url": "vinicius-de-moraes", "discography": ["a-arca-de-noe", "a-brusca-poesia-da-mulher-iii", "a-casa", "a-corujinha", "a-felicidade", "a-formiga", "a-hora-intima", "a-insensatez", "a-porta", "a-primavera", "a-pulga", "a-terra-prometida", "a-tonga-da-mironga-do-kabulete", "a-volta-da-mulher-morena", "abertura-estamos-ai-dia-de-criacao-tarde-em-ita", "alem-do-amor", "amigos-meus", "andam-dizendo", "apelo", "aquarela", "arrastao", "as-abelhas", "as-cores-de-abril", "aula-de-piano", "berimbau", "bocoche", "brigas-nunca-mais", "broto-maroto", "cala-meu-amor", "cancao-de-nos-dois", "cancao-em-modo-menor", "cancao-para-a-amiga-dormindo", "cancao-para-alguem", "canto-de-iemanja", "canto-de-ossanha", "canto-de-oxum", "canto-de-pedra-preta", "canto-de-xango", "carta-ao-tom", "carta-ao-tom-74-2", "carta-do-ausente", "catende", "chega-de-saudade", "como-dizia-o-poeta", "como-e-duro-trabalhar", "conjugacao-da-ausente", "cotidiano-n-2", "deixa", "desespero-da-piedade", "deve-ser-amor", "dia-da-criacao", "dialetica", "dora", "e-preciso-dizer-adeus", "elegia-desesperada", "elegia-na-morte-de-clodoaldo-pereira-da-silva-moraes-poeta-e-cidadao", "epitafio", "escravo-de-alegria", "eu-nao-existo-sem-voce", "eu-sei-que-vou-te-amar", "eu-te-amo-amor", "feijoada-a-minha-moda", "formosa", "garota-de-ipanema", "gente-humilde", "gilda", "insensatez", "januaria", "lamento-do-morro", "loira-ou-morena", "marcha-de-quarta-feira-de-cinzas", "medo-de-amar", "melancia-e-coco-verde", "menina-das-duas-trancas", "menininha", "mensagem-a-poesia", "meu-pai-oxala", "meu-pranto-rolou", "minha-namorada", "monologo-de-orfeu", "morena-flor", "mulher-carioca", "o-astronauta", "o-canto-de-oxum", "o-desespero-da-piedade", "o-filho-que-eu-quero-ter", "o-gato", "o-haver", "o-leao", "o-mais-que-perfeito", "o-pato-pateta", "o-pinguim", "o-pintinho", "o-poeta-aprendiz", "o-poeta-e-a-lua", "o-poeta-e-a-rosa", "o-porquinho", "o-relogio", "o-velho-e-a-flor", "o-vento", "odeon", "onde-anda-voce", "os-acrobatas", "para-viver-um-grande-amor", "pedro-meu-filho", "pela-luz-dos-olhos-teus", "planta-baixa", "poema-de-natal", "poema-dos-olhos-da-amada", "poema-enjoadinho", "poetica-i", "poetica-ii", "quatro-sonetos-de-meditacao", "queixa", "rancho-das-namoradas", "receita-de-mulher", "regra-tres", "rosa-de-hiroshima", "rosario", "samba-da-bencao", "samba-da-rosa", "samba-da-volta", "samba-de-gesse", "samba-de-orly", "samba-de-uma-nota-so", "samba-em-preludio", "samba-pra-endrigo", "se-ela-quisesse", "se-o-amor-pudesse", "se-todos-fossem-iguais-a-voce", "sei-la-a-vida-tem-sempre-razao", "seja-feliz", "sem-voce", "separacaoas-razoes-do-coracao", "serenata-do-adeus", "soneto-da-fidelidade", "soneto-da-mulhar-ideal", "soneto-da-separacao", "soneto-de-despedida", "soneto-de-fidelidade", "soneto-de-intimidade", "soneto-de-separacao", "soneto-de-vespera", "soneto-de-vinicius-dedicado-a-neruda", "soneto-do-amor-maior", "soneto-do-amor-total", "soneto-do-corifeu", "tarde-em-itapoa-2", "tempo-de-amor", "ternura", "tomara", "trecho", "tristeza", "tristeza-e-solidao", "um-homem-chamado-alfredo", "um-nome-de-mulher", "uma-mulher-no-meio-do-mar", "valsa-de-euridice", "valsinha", "voce-e-eu"]}}, "Hip-hop": {"Sabotage": {"url": "sabotage", "discography": ["a-banca-ratata-e-bicho-solto", "a-cultura", "aracnideo", "cabeca-de-nego", "cantando-pro-santo-2", "cigarro-mata", "cocaina", "como-um-missil", "dama-tereza", "dorobo", "enxame", "incentivando-o-som", "levada-segura", "love-song-a-maior-dor-de-um-homem-com-mano-brown", "maloca-e-mare-feat-rappin-hood-funk-buia", "missel", "monstro-invisivel-part-mc-hariel", "mosquito", "mun-ra", "na-zona-sul", "no-brooklin", "o-invasor", "o-gatilho", "o-gatilho-2", "o-jogo-e-pesado", "o-livro", "o-retorno-ac-dc-a-prisao", "pais-da-fome", "pais-da-fome-parte-2", "quem-viver-vera-part-dexter-dj-cia", "rap-e-compromisso", "sai-da-frente", "superar-feat-shyheim-dj-nuts", "tic-tac", "um-bom-lugar"]}, "Racionais Mc's": {"url": "racionais-mcs", "discography": ["instrumental", "1-por-amor-2-por-dinheiro", "12-de-outubro", "500-anos", "a-escolha-que-eu-fiz", "a-historia", "a-mente-do-vilao", "a-praca", "a-vida-e-desafio", "a-vitima", "amor-distante-mano-brown-solo", "artigo-157", "beco-sem-saida", "capitulo-4-versiculo-3", "coracao-barrabaz", "cores-valores-finado-neguin", "cores-valores-preto-e-amarelo", "cores-e-valores", "cores-e-valores-part-heliao", "crime-vai-o-crime-vem", "da-ponte-pra-ca", "de-volta-a-cena", "diario-de-um-detento", "estilo-cachorro", "eu-compro", "eu-te-disse", "eu-te-proponho", "expresso-meia-noite", "fim-de-semana-no-parque", "fio-da-navalha", "fone-intro", "formula-magica-da-paz", "genesis-intro", "hey-boy", "homem-na-estrada", "introducao", "jesus-chorou", "jorge-da-capadocia", "juri-racional", "madrugada-suspeita", "magico-de-oz", "mano-na-porta-do-bar", "maos", "mil-faces-de-um-homem-leal-marighella", "minha-oracao", "mulher-eletrica", "mulheres-vulgares", "racionais-mcs-na-feh-firmao", "negro-drama", "negro-limitado", "ninguem-pediu-sua-opiniao", "o-mal-e-o-bem", "otus-500", "oya", "panico-na-zona-sul", "parte-ii", "periferia-e-periferia", "preto-zica", "qual-mentira-vou-acreditar", "quanto-vale-o-show", "quem-procura-acha-sabedoria-de-vida-part-mano-brown", "racistas-otarios", "rapaz-comum", "salve", "somos-o-que-somos", "sou-mais-voce", "ta-na-cuva", "tempos-dificieis", "thats-my-way-ed-rock-part-seu-jorge", "to-ouvindo-alguem-me-chamar", "trilha", "trutas-e-quebradas", "umbabarauma-mano-brown-com-jorge-ben-jor", "vandalos", "vida-loka", "vida-loka-parte-ii", "vida-loka-intro", "vida-loka-tambem-ama", "vivao-e-vivendo", "voce-me-deve", "voz-ativa"]}, "Gabriel O Pensador": {"url": "gabriel-pensador", "discography": ["1-dose", "e-voce", "12-meses-por-ano", "175-nada-especial", "2345meia78", "a-cura-ta-no-coracao-part-cynthia-luz", "a-historia-de-pedro-vs-cliente", "abalando", "aglomeracao-a-2-com-ivete-sangalo", "ah", "amigo-urso-resposta-do-amigo-urso", "assaltram-a-gramatica-ii", "astronauta", "ate-quando", "bala-perdida", "boca-com-boca-com-nando-reis", "boca-seca", "bossa", "brasa", "brasil-500-anos", "brazuca", "brilho-cego-com-rogerio-flausino", "burn-babylon", "cachimbo-da-paz", "cachimbo-da-paz-2-part-lulu-santos-e-xama", "cachorrada", "cacimba-de-magoa", "cantao", "cara-feia", "cavaleiro-andante", "chega", "como-um-vicio", "correr-pro-abraco", "danca-do-desempregado", "dancando-com-a-vida", "deixa-quieto", "deixa-rolar", "dentro-de-voce", "do-nada", "e-pra-rir-ou-pra-chorar", "en-la-casa", "esperanduque", "estudo-errado", "eu-e-a-tabua", "faca-o-diabo-feliz", "fala-serio", "fdp", "fe-na-luta", "festa-da-musica-tupiniquim", "filho-da-patria-iludido", "firme-e-forte", "foi-nao-foi-feat-carlinhos-brown", "girl-from-garopaba", "giro", "hoje-eu-to-feliz-matei-o-presidente", "homem-nao-presta", "indecencia-militar", "inicio-da-musica-hoje-to-feliz-matei-o-presidente", "isso-aqui-e-familia", "jogador", "just-the-two-of-us-com-will-smith", "lata-velha", "lavagem-cerebral", "liberdade-part-armandinho", "linhas-tortas", "loraburra", "mandei-avisar", "mario", "martelo", "masturbacao-mental", "matador", "medley-back-to-back", "mentiras-do-brasil", "mi-casa-su-casa", "muito-orgulho-meu-pai", "na-casa-da-vovo-bisa", "na-palma-da-mao", "nadegas-a-declarar", "nao-da-pra-ser-feliz", "no-ritmo-no-tempo-part-conecrewdiretoria", "nunca-serao", "nunca-tenha-medo-part-black-alien", "o-cahimbo-da-paz", "o-resto-do-mundo", "obrigado-mar-por-isso-tudo-part-makua-rothman", "palavras-repetidas", "pao-de-cada-dia", "passaporte-para-a-fe-com-macacko", "patria-que-me-pariu", "patriota-comunista", "paz", "pega-ladrao", "pimenta-e-sal", "porca-miseria", "pra-onde-vai", "profecia", "rabo-de-saia", "racismo-e-burrice-nova-versao-de-lavagem-cerebral", "rap-do-feio", "rap-do-soletrando", "retrato-de-um-playboy-juventude-perdida", "retrato-de-um-playboy-parte-2", "rockixe", "se-liga-ai", "sei-la", "sem-crise", "sem-neurose", "sem-parar", "sem-saude", "sim-nao-indiferente", "sobrevivente", "societys-victim", "sorria", "surfista-solitario", "tas-a-ver", "tem-alguem-ai", "tempestade", "to-contigo-e-nao-abro", "to-feliz", "to-feliz-matei-o-presidente-2", "to-vazando", "topo-do-mundo-fundo-do-poco", "tudo-certo", "tudo-na-mente", "ultimamente", "um-minuto", "vamo-ai-part-ponto-de-equilibrio-e-gabz", "xaxado-xiado"]}}, "Rock": {"Planet Hemp": {"url": "planet-hemp", "discography": ["100-hardcore", "a-culpa-e-de-quem", "ainda-rmx", "amnesia", "bala-perdida", "contexto", "deisdazseis", "dig-dig-dig-hempa", "distopia-part-criolo", "eles-sentem-tambem", "ex-quadrilha-da-fumaca", "fim-do-fim", "four-track", "futuro-do-pais", "gorilla-grip", "hc3", "hemp-family", "hip-hop-rio", "jardineiro", "legalize-ja", "mantenha-o-respeito", "mao-na-cabeca", "marcelo-yuka", "mary-jane", "meu-barrio-feat-trueno", "mutha-fuckin-racists", "nao-compre-plante", "nao-vamos-desistir-part-black-alien", "nega-do-cabelo-duro", "ninguem-segura-a-gente", "nunca-tenha-medo-part-posdnuos", "o-bicho-ta-pegando", "o-ritmo-e-a-raiva-part-black-alien", "o-sagaz-homem-fumaca", "onda-forte-rmx", "paga-pau", "planet-hemp", "planeta-maconha", "procedencia-c-d", "puta-disfarcada", "puxa-fumo", "quem-tem-ceda-tablatura", "quem-tem-seda", "rappers-reais", "raprockandrollpsicodeliahardcoregga", "remedinho", "se-liga", "skunk", "stab", "taca-fogo", "test-drive-de-freio-de-camburao", "top-top", "veias-abertas-part-tantao-e-os-fita"]}, "Chico Science & Nação Zumbi": {"url": "chico-science-nacao-zumbi", "discography": ["a-cidade", "amor-de-muito", "antene-se", "coco-dub-afrociberdelia", "computadores-fazem-arte", "corpo-de-lama", "crianca-de-domingo", "da-lama-ao-caos", "enquanto-o-mundo-explode", "etnia", "interlude-zumbi", "maco", "malungo", "maracatu-atomico", "maracatu-de-tiro-certeiro", "mateus-enter-intro", "monologo-ao-pe-do-ouvido-banditismo-por-uma-questao-de-classe", "o-cidadao-do-mundo", "o-encontro-de-isaac-asimov-com-santos-dumont", "o-encontro-de-isaac-asimov-com-santos-dumont-no-ceu", "prototipo-sambadelico-de-mensagem-digital", "rios-pontes-e-overdrives", "risoflora", "samba-de-lado", "samidarish", "sangue-de-bairro", "sobremesa", "todos-estao-surdos", "um-passeio-no-mundo-livre"]}, "Charlie Brown Jr": {"url": "charlie-brown-jr", "discography": ["121", "333", "333-tablatura", "a-banca", "a-banca-acustico-mtv", "a-grande-volta", "a-mais-linda-do-bar", "abrir-seus-olhos", "amor-pelas-ruas", "aquela-paz", "aquele-velho-carteado-e-algumas-manobrinhas", "baader-meinhof-blues", "bahia", "be-myself", "beco-sem-saida", "bocas-ordinarias-guerrilha", "bons-aliados", "buscando-um-novo-rumo", "cada-cabeca-falante-tem-sua-tromba-de-elefante", "cafe-fundation", "camisa-10-joga-bola-ate-na-chuva-bomba-sonica", "camisa-preta", "cancao-do-senhor-da-guerra", "ceu-azul", "champanhe-e-agua-benta", "charlie-brown-jr", "charlie-brown-jr-tablatura", "chegou-quem-faltava", "cheia-de-vida", "cheirando-cola", "cidadao-comum-refem", "cidade-grande", "com-a-boca-amargando", "com-minha-loucura-faco-meu-dinheiro-com-meu-dinheiro-faco-minhas-loucuras", "comigo-ninguem-tira-onda", "como-tudo-deve-ser", "confisco", "contrastes-da-vida", "coracao-satanico-part-marcelo-nova", "corra-vagabundo", "criando-anticorpos", "cruzei-uma-doida", "curva-de-hill", "de-olhos-abertos", "depois-de-uma-bela-session-um-belo-sofa-pizza-e-grafite", "descubra-o-que-ha-de-errado-com-voce", "deu-entrada-pra-subir", "deus-me-deu-um-dom-chorao-e-kikolatino", "eu-sou-chorao", "di-sk8-eu-vou", "dias-de-luta-dias-de-gloria", "dias-de-luta-dias-de-gloria-versao-2012", "direto-e-reto-sempre", "do-jeito-que-eu-gosto-do-jeito-que-eu-quero", "do-surf", "dona-do-meu-pensamento", "e-quente", "6-ela-vai-voltar-todos-os-defeitos-de-uma-mulher-perfeita", "escalas-tropicais", "essa-e-pra-quem-ficou-pra-tras", "eu-protesto", "eu-vim-de-santos-sou-charlie-brown", "falar-falar", "festa", "fichado", "filho-de-guerreiro", "fina-arte", "fogo-na-bomba", "fundao", "gimme-o-anel", "green-goes", "hei-arreia", "historia-mal-escrita", "historia-sem-final", "hoje", "hoje-de-noite", "hoje-eu-acordei-feliz", "hoje-eu-so-procuro-a-minha-paz", "hoje-sou-eu-que-nao-mais-te-quero", "cada-um-no-seu-mundo", "homenagem-ao-santos-futebol-clube", "i-fell-so-good-today", "i-fell-so-good-today-uma-crianca-com-o-seu-olhar", "inabalavelmente", "indicados-para-o-premio-nobel-da-paz", "legendarios", "liberdade-acima-de-tudo", "liberdade-e-tudo", "local", "lombra", "longe-de-voce", "lugar-ao-sol", "lugar-ao-sol-tablatura", "lutar-pelo-que-e-meu", "malabarizandoquem-e-de-fe-continua-com-a-gente", "malokero-sk8-board", "mantenha-a-duvida", "marcas-do-que-se-foi", "marginal-alado", "me-deixa-part-falcao", "me-encontra", "menina-linda-mega-special-girl", "meu-novo-mundo", "molengols-groove", "muito-antes-que-voce", "mundo-deserto", "my-mini-ramp", "na-palma-da-mao-o-ragga-da-baixada", "nada-e-impossivel", "nao-deixe-o-mar-te-engolir", "nao-e-serio", "nao-fure-os-olhos-da-verdade", "nao-uso-sapato", "nao-viva-em-vao", "ninguem-entende-voce", "no-desafio-ibiraboys-a-uniao-prevalece", "no-passo-a-passo", "nua-linda-e-inigualavel", "o-coro-vai-come", "o-dom-a-inteligencia-e-a-voz", "o-errado-que-deu-certo", "o-futuro-e-o-labirinto-pra-quem-nao-sabe-o-que-quer", "o-lado-certo-da-vida-errada", "o-lixo-e-o-luxo", "o-mundo-explodiu-la-fora", "o-nosso-blues", "o-penetra", "o-preco", "o-que-e-da-casa-e-da-casa-papo-reto", "o-que-e-da-casa-e-da-casa", "o-que-ela-gosta-e-de-barriga", "o-universo-a-nosso-favor", "oba-la-vem-ela", "onde-esta-o-mundo-bom-living-in-l-a", "5-onde-nao-existe-a-paz-nao-existe-o-amor", "os-cortes", "ouviu-se-falar", "papo-reto", "paranormal", "passo-forte-kikolatino-part-chorao", "peso-da-batida-do-errado-que-deu-certo", "pontes-indestrutiveis", "pra-mais-tarde-fazermos-a-cabeca", "pra-nao-dizer-que-eu-nao-falei-das-flores", "proibida-pra-mim", "puro-sangue", "puxa-carro", "quando-tudo-aconteceu", "que-especie-de-vermes-sao-voces", "quebra-mar", "quinta-feira", "rale", "resolva-o-meu-problema-ai-tablatura", "resolve-o-meu-problema-ai", "ritmo-ritual-e-responsa", "rock-star", "rubao-o-dono-do-mundo", "samba-makossa", "samba-triste", "sem-medo-da-escuridao", "senhor-do-tempo", "sheik-tosado", "sino-dourado-letras", "skate-vibration", "skateboard-amor-eterno", "so-existe-o-agora", "so-far-away", "so-lazer", "so-os-loucos-sabem", "so-por-uma-noite", "so-por-uma-noite-tablatura-para-baixo", "so-pra-vadiar", "somos-extremes-no-esporte-e-na-musica", "somos-poucos-mas-somos-loucos", "sou-quem-eu-sou-o-que-e-seu-tambem-e-meu-e-o-que-e-meu-nao-e-nosso", "t-f-d-p", "talvez-a-metade-do-caminho", "tamo-ai-na-atividade", "tarja-preta", "te-levar", "todos-iguais-403", "too-fast-live-too-young-too-die", "transar-no-escuro", "tributo-171", "tributo-ao-frango-da-malasia", "trocando-uma-ideia-com-deus", "tu-vai-de-limosine-e-eu-vou-de-trem", "tudo-igual", "tudo-mudar", "tudo-pro-alto", "tudo-que-ela-gosta-de-escutar", "um-dia-a-gente-se-encontra", "uma-crianca-com-seu-olhar", "uma-so-vida-pra-viver-tenho-sede-nela-eu-vou", "uniao", "vao-fazer-de-novo", "vao-fazer-de-novo-paranormal-attack-remix", "vem-ser-minha", "vicios-e-virtudescorreta", "vida-de-magnata", "vinheta-uniao", "vivendo-a-vida-numa-louca-viagem", "vivendo-nesse-absurdo", "viver-dias-de-sol", "voce-por-perto", "voce-vai-de-limusine-eu-vou-de-trem", "vou-me-embriagar-de-voce", "zoio-de-lula-1"]}, "Renato Russo": {"url": "renato-russo", "discography": ["a-carta", "a-cruz-e-a-espada", "and-so-it-goes", "boomerang-blues", "cathedral-song", "celeste", "change-partners", "cherish", "close-the-door-lightly-when-you-go", "clothes-of-sand", "come-fa-unonda", "dolcissima-maria", "due", "e-tu-come-stai", "esquadros", "gente", "gente-humilde-letras", "hey-thats-no-way-to-say-goodbye", "hoje", "i-get-along-without-you-very-well", "i-love-you-porgy", "i-venti-del-cuore-2", "if-i-loved-you", "if-tomorrow-never-comes", "if-you-see-him-say-hello", "il-mondo-degli-altri", "la-forza-della-vita", "la-solitudine", "la-vita-e-adesso", "lets-face-the-music-and-dance", "lettera", "like-a-lover", "love-is", "mais-uma-vez", "miss-celies-blues", "mumias", "nada-por-mim", "nao-ditas-por-mim", "old-friend", "paper-of-pins", "passera", "piu-o-meno", "quando-eu-estiver-cantandoendless-love", "say-it-isnt-so", "scrivimi", "send-in-the-clowns", "so-louco", "somewhere", "somewhere-in-my-broken-heart", "strani-amori", "summertime-com-cida-moreira", "the-ballad-of-the-sad-young-men", "the-dance", "the-heart-of-the-matter", "thunder-road", "ti-chiedo-onesta", "ti-chiedo-onesta-te-peco-honestidade-traducao", "i-venti-del-cuore", "wavecome-fa-unonda", "when-you-wish-upon-a-star"]}, "Cazuza": {"url": "cazuza", "discography": ["a-inocencia-do-prazer-gravada-por-dulce-quental", "a-orelha-de-euridice", "amigo-caco", "amor-quente", "amor-amor", "androide-sem-par", "as-mocas-do-centro", "ataque-de-nervos", "aula", "azul-e-amarelo", "baby-lonest", "balada-de-um-vagabundo", "balada-do-esplanada", "bete-balanco", "bilhetinho-azul", "blues-da-piedade", "blues-do-ano-2000", "blues-do-iniciante", "boa-vida", "boas-novas", "bobeira", "brasil", "brasil-tv", "bruma", "burguesia", "camila-camila", "carreirinha", "carta-dani", "cartao-postal", "cavalos-calados", "cobais-de-deus", "codinome-beija-flor", "como-ja-dizia-djavan", "completamente-blue", "conforto-gravada-por-cris-braun", "culpa-de-estimacao", "cumplice", "desastre-mental", "dia-dos-namorados-part-ney-matogrsosso", "dolorosa", "doralinda", "down-em-mim", "e-estamos-conversados", "eclipse-oculto", "esse-cara", "eu-agradeco", "eu-queria-ter-uma-bomba", "eu-quero-alguem", "exagerado", "exagerado-3-0", "faz-parte-do-meu-show", "filho-unico", "filosofia-de-calcada", "garota-de-bauru", "guerra-civil", "heavy-love", "hei-rei", "ideologia", "incapacidade-de-amar", "jovem", "largado-no-mundo", "luz-negra", "maior-abandonado", "maioridade", "mais-feliz", "mal-nenhum", "malandragem", "manhata", "mania-de-cantar", "medieval-ii", "menina-mimada", "mina", "minha-flor-meu-bebe", "modernidade", "mulher-sem-razao", "nabucodonosor", "nao-amo-ninguem", "nao-ha-perdao-para-o-chato", "narciso", "o-assassinato-da-flor", "o-brasil-vai-ensinar-o-mundo", "o-lobo-mau-da-ucrania", "o-mundo-e-um-moinho", "o-nosso-amor-a-gente-inventa-estoria-romantica", "o-tempo-nao-para", "obrigado-por-ter-se-mandado", "ombra-mai-fu", "orelha-de-euridice", "oriental-ii", "paixao", "pedaco-do-meu-coracao", "pedra-flor-e-espinho", "perto-do-fogo", "poema", "por-ai", "por-quase-um-segundo", "por-que-a-gente-e-assim", "portuga", "preciso-dizer-que-te-amo", "preconceito", "pro-dia-nascer-feliz", "quando-eu-estiver-cantando", "quarta-feira", "quase-um-segundo", "que-o-deus-venha", "querido-diario-topicos-para-uma-semana-utopica-poema-inedito", "ritual", "rock-da-descerebracao", "sem-vergonha", "so-as-maes-sao-felizes", "so-se-for-a-dois", "solidao-que-nada", "sorte-ou-azar", "summertime", "tapas-na-cara-gravada-por-angela-maria", "todo-o-amor-que-houver-nessa-vida", "tudo-e-amor", "um-trem-para-as-estrelas", "uma-so-voz", "vai-a-luta", "vida-facil", "vida-louca-vida", "vinganca-boba", "voce-se-parece-com-todo-mundo"]}, "O Rappa": {"url": "o-rappa", "discography": ["7-vezes", "a-feira", "a-noite", "a-todas-as-comunidades-do-engenho-novo", "anjos-pra-quem-tem-fe", "auto-reverse", "biterrusso-champagne", "boa-noite-xango", "brixton-bronx-ou-baixada", "candidato-cao-cao", "cataqueses-do-medo", "coincidencias-e-paixoes", "como-uma-bala-perdida", "cristo-e-oxala", "cruz-de-tecido", "deus-lhe-pague", "documento", "doutor-sim-senhor", "e-preciso-mais-som", "em-busca-do-porrao", "eu-nao-sei-mentir-direito", "eu-quero-ver-gol", "farpa-cortante", "favela", "fica-doido-varrido", "fininho-da-vida", "fogo-cruzado", "fronteira-d-u-c-a", "hey-joe", "hostia", "ile-aye", "instinto-coletivo-s-erros", "intervalo-entre-carros", "lado-b-lado-a", "lei-da-sobrevivencia", "linha-vermelha", "linha-vermelha-tablatura", "maneiras-2", "mar-de-gente", "maria", "o-rappa-me-deixa", "meu-mundo-e-o-barro", "meu-santo-ta-cansado", "milagre", "minha-alma-a-paz-que-eu-nao-quero", "miseria-s-a", "mitologia-gerimum", "monstro-invisivel", "mundo-negro", "na-frente-do-reto", "na-horda", "na-palma-da-mao", "nao-perca-as-criancas-de-vista", "nao-vao-me-matar", "ninguem-regula-a-america", "no-de-fumaca", "o-homem-amarelo", "o-homem-bomba", "o-horizonte-e-logo-ali", "o-novo-ja-nasce-velho", "o-que-sobrou-do-ceu", "o-salto", "o-salto-2", "obvio", "oia-o-rappa", "papo-de-surdo-e-mudo", "para-pegador", "pescador-de-ilusoes", "prece-prece-sample-anjos-pra-quem-tem-fe-part-tuyo", "r-a-m", "respeito-pela-mais-bela", "reza-vela", "reza-vela-norte-nordeste-me-veste", "rodo-cotidiano", "se-nao-avisar-o-bicho-pega", "sentimento", "sequencia-terminal", "skunk-jammin", "sujo", "suplica-cearense", "take-it-easy-my-brother-charles", "todo-camburao-tem-um-pouco-de-navio-negreiro", "tribunal-de-rua", "tumulto", "um-dia-lindo-part-edi-rock", "uma-ajuda", "uma-vida-so", "vapor-barato", "varios-holofotes", "vem-pra-rua-jingle-fiat", "verdade-de-feirante", "vida-rasteja", "vinheta"]}}}